{
	"type": "animation",
	"frames": [
		{
			"ATTOVERCOG": {
				"pos": [0,-0,30],
				"rot": [1,0,0,0]
			},
			"head": {
				"pos": [0,0.001912,6.000518],
				"rot": [1,-0.000093,0.000145,0.000733]
			},
			"leg1": {
				"pos": [-3,-9,2.5],
				"rot": [1,0,0,0]
			},
			"leg2": {
				"pos": [-9,-3,2.5],
				"rot": [1,0,0,0]
			},
			"leg3": {
				"pos": [-9,3,2.5],
				"rot": [1,0,0,0]
			},
			"leg4": {
				"pos": [-3,9,2.5],
				"rot": [1,0,0,0]
			},
			"leg5": {
				"pos": [3,9,2.5],
				"rot": [1,0,0,0]
			},
			"leg6": {
				"pos": [9,3,2.5],
				"rot": [1,0,0,0]
			},
			"leg7": {
				"pos": [9,-3,2.5],
				"rot": [1,0,0,0]
			},
			"leg8": {
				"pos": [3.016188,-9.006338,2.549716],
				"rot": [0.999981,0.000529,-0.001037,0.006081]
			}
		},
		{
			"ATTOVERCOG": {
				"pos": [0,-0,30],
				"rot": [1,0,0,0]
			},
			"head": {
				"pos": [0,0.007682,6.002100],
				"rot": [0.999995,-0.000376,0.000581,0.002947]
			},
			"leg1": {
				"pos": [-3,-9,2.5],
				"rot": [1,0,0,0]
			},
			"leg2": {
				"pos": [-9,-3,2.5],
				"rot": [1,0,0,0]
			},
			"leg3": {
				"pos": [-9,3,2.5],
				"rot": [1,0,0,0]
			},
			"leg4": {
				"pos": [-3,9,2.5],
				"rot": [1,0,0,0]
			},
			"leg5": {
				"pos": [3,9,2.5],
				"rot": [1,0,0,0]
			},
			"leg6": {
				"pos": [9,3,2.5],
				"rot": [1,0,0,0]
			},
			"leg7": {
				"pos": [9,-3,2.5],
				"rot": [1,0,0,0]
			},
			"leg8": {
				"pos": [3.064908,-9.025414,2.699342],
				"rot": [0.999692,0.002196,-0.004120,0.024387]
			}
		},
		{
			"ATTOVERCOG": {
				"pos": [0,-0,30],
				"rot": [1,0,0,0]
			},
			"head": {
				"pos": [0,0.017346,6.004780],
				"rot": [0.999977,-0.000854,0.001309,0.006656]
			},
			"leg1": {
				"pos": [-3,-9,2.5],
				"rot": [1,0,0,0]
			},
			"leg2": {
				"pos": [-9,-3,2.5],
				"rot": [1,0,0,0]
			},
			"leg3": {
				"pos": [-9,3,2.5],
				"rot": [1,0,0,0]
			},
			"leg4": {
				"pos": [-3,9,2.5],
				"rot": [1,0,0,0]
			},
			"leg5": {
				"pos": [3,9,2.5],
				"rot": [1,0,0,0]
			},
			"leg6": {
				"pos": [9,3,2.5],
				"rot": [1,0,0,0]
			},
			"leg7": {
				"pos": [9,-3,2.5],
				"rot": [1,0,0,0]
			},
			"leg8": {
				"pos": [3.144124,-9.056428,2.942624],
				"rot": [0.998479,0.005145,-0.008999,0.054149]
			}
		},
		{
			"ATTOVERCOG": {
				"pos": [0,-0,30],
				"rot": [1,0,0,0]
			},
			"head": {
				"pos": [0,0.030907,6.008593],
				"rot": [0.999926,-0.001534,0.002324,0.011860]
			},
			"leg1": {
				"pos": [-3,-9,2.5],
				"rot": [1,0,0,0]
			},
			"leg2": {
				"pos": [-9,-3,2.5],
				"rot": [1,0,0,0]
			},
			"leg3": {
				"pos": [-9,3,2.5],
				"rot": [1,0,0,0]
			},
			"leg4": {
				"pos": [-3,9,2.5],
				"rot": [1,0,0,0]
			},
			"leg5": {
				"pos": [3,9,2.5],
				"rot": [1,0,0,0]
			},
			"leg6": {
				"pos": [9,3,2.5],
				"rot": [1,0,0,0]
			},
			"leg7": {
				"pos": [9,-3,2.5],
				"rot": [1,0,0,0]
			},
			"leg8": {
				"pos": [3.247734,-9.096995,3.260826],
				"rot": [0.995504,0.009439,-0.015112,0.093031]
			}
		},
		{
			"ATTOVERCOG": {
				"pos": [0,-0,30],
				"rot": [1,0,0,0]
			},
			"head": {
				"pos": [0,0.048333,6.013565],
				"rot": [0.999818,-0.002424,0.003618,0.018550]
			},
			"leg1": {
				"pos": [-3,-9,2.5],
				"rot": [1,0,0,0]
			},
			"leg2": {
				"pos": [-9,-3,2.5],
				"rot": [1,0,0,0]
			},
			"leg3": {
				"pos": [-9,3,2.5],
				"rot": [1,0,0,0]
			},
			"leg4": {
				"pos": [-3,9,2.5],
				"rot": [1,0,0,0]
			},
			"leg5": {
				"pos": [3,9,2.5],
				"rot": [1,0,0,0]
			},
			"leg6": {
				"pos": [9,3,2.5],
				"rot": [1,0,0,0]
			},
			"leg7": {
				"pos": [9,-3,2.5],
				"rot": [1,0,0,0]
			},
			"leg8": {
				"pos": [3.365107,-9.142949,3.621296],
				"rot": [0.990232,0.014877,-0.021635,0.136938]
			}
		},
		{
			"ATTOVERCOG": {
				"pos": [0,-0,30],
				"rot": [1,0,0,0]
			},
			"head": {
				"pos": [0,0.069551,6.019717],
				"rot": [0.999624,-0.003530,0.005178,0.026696]
			},
			"leg1": {
				"pos": [-3,-9,2.5],
				"rot": [1,0,0,0]
			},
			"leg2": {
				"pos": [-9,-3,2.5],
				"rot": [1,0,0,0]
			},
			"leg3": {
				"pos": [-9,3,2.5],
				"rot": [1,0,0,0]
			},
			"leg4": {
				"pos": [-3,9,2.5],
				"rot": [1,0,0,0]
			},
			"leg5": {
				"pos": [3,9,2.5],
				"rot": [1,0,0,0]
			},
			"leg6": {
				"pos": [9,3,2.5],
				"rot": [1,0,0,0]
			},
			"leg7": {
				"pos": [9,-3,2.5],
				"rot": [1,0,0,0]
			},
			"leg8": {
				"pos": [3.482481,-9.188904,3.981768],
				"rot": [0.982944,0.020896,-0.027693,0.180605]
			}
		},
		{
			"ATTOVERCOG": {
				"pos": [0,-0,30],
				"rot": [1,0,0,0]
			},
			"head": {
				"pos": [0,0.094436,6.027058],
				"rot": [0.999307,-0.004860,0.006984,0.036252]
			},
			"leg1": {
				"pos": [-3,-9,2.5],
				"rot": [1,0,0,0]
			},
			"leg2": {
				"pos": [-9,-3,2.5],
				"rot": [1,0,0,0]
			},
			"leg3": {
				"pos": [-9,3,2.5],
				"rot": [1,0,0,0]
			},
			"leg4": {
				"pos": [-3,9,2.5],
				"rot": [1,0,0,0]
			},
			"leg5": {
				"pos": [3,9,2.5],
				"rot": [1,0,0,0]
			},
			"leg6": {
				"pos": [9,3,2.5],
				"rot": [1,0,0,0]
			},
			"leg7": {
				"pos": [9,-3,2.5],
				"rot": [1,0,0,0]
			},
			"leg8": {
				"pos": [3.586091,-9.229470,4.299970],
				"rot": [0.974843,0.026668,-0.032623,0.218874]
			}
		},
		{
			"ATTOVERCOG": {
				"pos": [0,-0,30],
				"rot": [1,0,0,0]
			},
			"head": {
				"pos": [0,0.122809,6.035586],
				"rot": [0.998827,-0.006418,0.009013,0.047149]
			},
			"leg1": {
				"pos": [-3,-9,2.5],
				"rot": [1,0,0,0]
			},
			"leg2": {
				"pos": [-9,-3,2.5],
				"rot": [1,0,0,0]
			},
			"leg3": {
				"pos": [-9,3,2.5],
				"rot": [1,0,0,0]
			},
			"leg4": {
				"pos": [-3,9,2.5],
				"rot": [1,0,0,0]
			},
			"leg5": {
				"pos": [3,9,2.5],
				"rot": [1,0,0,0]
			},
			"leg6": {
				"pos": [9,3,2.5],
				"rot": [1,0,0,0]
			},
			"leg7": {
				"pos": [9,-3,2.5],
				"rot": [1,0,0,0]
			},
			"leg8": {
				"pos": [3.665307,-9.260487,4.543252],
				"rot": [0.967601,0.031354,-0.036111,0.247915]
			}
		},
		{
			"ATTOVERCOG": {
				"pos": [0,-0,30],
				"rot": [1,0,0,0]
			},
			"head": {
				"pos": [0,0.154432,6.045291],
				"rot": [0.998144,-0.008208,0.011235,0.059293]
			},
			"leg1": {
				"pos": [-3,-9,2.5],
				"rot": [1,0,0,0]
			},
			"leg2": {
				"pos": [-9,-3,2.5],
				"rot": [1,0,0,0]
			},
			"leg3": {
				"pos": [-9,3,2.5],
				"rot": [1,0,0,0]
			},
			"leg4": {
				"pos": [-3,9,2.5],
				"rot": [1,0,0,0]
			},
			"leg5": {
				"pos": [3,9,2.5],
				"rot": [1,0,0,0]
			},
			"leg6": {
				"pos": [9,3,2.5],
				"rot": [1,0,0,0]
			},
			"leg7": {
				"pos": [9,-3,2.5],
				"rot": [1,0,0,0]
			},
			"leg8": {
				"pos": [3.714026,-9.279561,4.692877],
				"rot": [0.962698,0.034350,-0.038131,0.265668]
			}
		},
		{
			"ATTOVERCOG": {
				"pos": [0,-0,30],
				"rot": [1,0,0,0]
			},
			"head": {
				"pos": [0,0.189002,6.056141],
				"rot": [0.997218,-0.010226,0.013615,0.072565]
			},
			"leg1": {
				"pos": [-3,-9,2.5],
				"rot": [1,0,0,0]
			},
			"leg2": {
				"pos": [-9,-3,2.5],
				"rot": [1,0,0,0]
			},
			"leg3": {
				"pos": [-9,3,2.5],
				"rot": [1,0,0,0]
			},
			"leg4": {
				"pos": [-3,9,2.5],
				"rot": [1,0,0,0]
			},
			"leg5": {
				"pos": [3,9,2.5],
				"rot": [1,0,0,0]
			},
			"leg6": {
				"pos": [9,3,2.5],
				"rot": [1,0,0,0]
			},
			"leg7": {
				"pos": [9,-3,2.5],
				"rot": [1,0,0,0]
			},
			"leg8": {
				"pos": [3.730214,-9.285899,4.742594],
				"rot": [0.960993,0.035363,-0.038780,0.271547]
			}
		},
		{
			"ATTOVERCOG": {
				"pos": [0,-0,30],
				"rot": [1,0,0,0]
			},
			"head": {
				"pos": [0,0.226152,6.068093],
				"rot": [0.996016,-0.012467,0.016115,0.086820]
			},
			"leg1": {
				"pos": [-3,-9,2.5],
				"rot": [1,0,0,0]
			},
			"leg2": {
				"pos": [-9,-3,2.5],
				"rot": [1,0,0,0]
			},
			"leg3": {
				"pos": [-9,3,2.5],
				"rot": [1,0,0,0]
			},
			"leg4": {
				"pos": [-3,9,2.5],
				"rot": [1,0,0,0]
			},
			"leg5": {
				"pos": [3,9,2.5],
				"rot": [1,0,0,0]
			},
			"leg6": {
				"pos": [9,3,2.5],
				"rot": [1,0,0,0]
			},
			"leg7": {
				"pos": [9.015450,-3.006488,2.556190],
				"rot": [0.999991,-0.000950,0.000649,0.004022]
			},
			"leg8": {
				"pos": [3.729520,-9.276863,4.692878],
				"rot": [0.962760,0.034017,-0.036916,0.265655]
			}
		},
		{
			"ATTOVERCOG": {
				"pos": [0,-0,30],
				"rot": [1,0,0,0]
			},
			"head": {
				"pos": [0,0.265454,6.081083],
				"rot": [0.994508,-0.014916,0.018692,0.101890]
			},
			"leg1": {
				"pos": [-3,-9,2.5],
				"rot": [1,0,0,0]
			},
			"leg2": {
				"pos": [-9,-3,2.5],
				"rot": [1,0,0,0]
			},
			"leg3": {
				"pos": [-9,3,2.5],
				"rot": [1,0,0,0]
			},
			"leg4": {
				"pos": [-3,9,2.5],
				"rot": [1,0,0,0]
			},
			"leg5": {
				"pos": [3,9,2.5],
				"rot": [1,0,0,0]
			},
			"leg6": {
				"pos": [9,3,2.5],
				"rot": [1,0,0,0]
			},
			"leg7": {
				"pos": [9.061948,-3.026405,2.725298],
				"rot": [0.999859,-0.003840,0.002555,0.016132]
			},
			"leg8": {
				"pos": [3.726944,-9.249670,4.543252],
				"rot": [0.967825,0.030110,-0.031217,0.247860]
			}
		},
		{
			"ATTOVERCOG": {
				"pos": [0,-0,30],
				"rot": [1,0,0,0]
			},
			"head": {
				"pos": [0,0.306424,6.095037],
				"rot": [0.992679,-0.017554,0.021303,0.117583]
			},
			"leg1": {
				"pos": [-3,-9,2.5],
				"rot": [1,0,0,0]
			},
			"leg2": {
				"pos": [-9,-3,2.5],
				"rot": [1,0,0,0]
			},
			"leg3": {
				"pos": [-9,3,2.5],
				"rot": [1,0,0,0]
			},
			"leg4": {
				"pos": [-3,9,2.5],
				"rot": [1,0,0,0]
			},
			"leg5": {
				"pos": [3,9,2.5],
				"rot": [1,0,0,0]
			},
			"leg6": {
				"pos": [9,3,2.5],
				"rot": [1,0,0,0]
			},
			"leg7": {
				"pos": [9.137550,-3.059704,3.000258],
				"rot": [0.999305,-0.008636,0.005505,0.035839]
			},
			"leg8": {
				"pos": [3.721617,-9.205453,4.299970],
				"rot": [0.975240,0.024225,-0.021674,0.218746]
			}
		},
		{
			"ATTOVERCOG": {
				"pos": [0,-0,30],
				"rot": [1,0,0,0]
			},
			"head": {
				"pos": [0,0.348534,6.109859],
				"rot": [0.990526,-0.020353,0.023903,0.133690]
			},
			"leg1": {
				"pos": [-3,-9,2.5],
				"rot": [1,0,0,0]
			},
			"leg2": {
				"pos": [-9,-3,2.5],
				"rot": [1,0,0,0]
			},
			"leg3": {
				"pos": [-9,3,2.5],
				"rot": [1,0,0,0]
			},
			"leg4": {
				"pos": [-3,9,2.5],
				"rot": [1,0,0,0]
			},
			"leg5": {
				"pos": [3,9,2.5],
				"rot": [1,0,0,0]
			},
			"leg6": {
				"pos": [9,3,2.5],
				"rot": [1,0,0,0]
			},
			"leg7": {
				"pos": [9.236436,-3.104920,3.359893],
				"rot": [0.997944,-0.015082,0.009077,0.061632]
			},
			"leg8": {
				"pos": [3.712580,-9.147620,3.981768],
				"rot": [0.983403,0.017426,-0.008719,0.180384]
			}
		},
		{
			"ATTOVERCOG": {
				"pos": [0,-0,30],
				"rot": [1,0,0,0]
			},
			"head": {
				"pos": [0,0.391223,6.125441],
				"rot": [0.988060,-0.023280,0.026451,0.149989]
			},
			"leg1": {
				"pos": [-3,-9,2.5],
				"rot": [1,0,0,0]
			},
			"leg2": {
				"pos": [-9,-3,2.5],
				"rot": [1,0,0,0]
			},
			"leg3": {
				"pos": [-9,3,2.5],
				"rot": [1,0,0,0]
			},
			"leg4": {
				"pos": [-3,9,2.5],
				"rot": [1,0,0,0]
			},
			"leg5": {
				"pos": [3,9,2.5],
				"rot": [1,0,0,0]
			},
			"leg6": {
				"pos": [9,3,2.5],
				"rot": [1,0,0,0]
			},
			"leg7": {
				"pos": [9.348456,-3.158845,3.767301],
				"rot": [0.995527,-0.022606,0.012722,0.090849]
			},
			"leg8": {
				"pos": [3.698976,-9.082106,3.621297],
				"rot": [0.990538,0.010993,0.006532,0.136642]
			}
		},
		{
			"ATTOVERCOG": {
				"pos": [0,-0,30],
				"rot": [1,0,0,0]
			},
			"head": {
				"pos": [0,0.433911,6.141665],
				"rot": [0.985309,-0.026294,0.028909,0.166253]
			},
			"leg1": {
				"pos": [-3,-9,2.5],
				"rot": [1,0,0,0]
			},
			"leg2": {
				"pos": [-9,-3,2.5],
				"rot": [1,0,0,0]
			},
			"leg3": {
				"pos": [-9,3,2.5],
				"rot": [1,0,0,0]
			},
			"leg4": {
				"pos": [-3,9,2.5],
				"rot": [1,0,0,0]
			},
			"leg5": {
				"pos": [3,9,2.5],
				"rot": [1,0,0,0]
			},
			"leg6": {
				"pos": [9,3,2.5],
				"rot": [1,0,0,0]
			},
			"leg7": {
				"pos": [9.460477,-3.216843,4.174708],
				"rot": [0.992178,-0.030346,0.015930,0.120034]
			},
			"leg8": {
				"pos": [3.680303,-9.016591,3.260826],
				"rot": [0.995425,0.005946,0.022302,0.092722]
			}
		},
		{
			"ATTOVERCOG": {
				"pos": [0,-0,30],
				"rot": [1,0,0,0]
			},
			"head": {
				"pos": [0,0.476021,6.158407],
				"rot": [0.982316,-0.029351,0.031242,0.182259]
			},
			"leg1": {
				"pos": [-3,-9,2.5],
				"rot": [1,0,0,0]
			},
			"leg2": {
				"pos": [-9,-3,2.5],
				"rot": [1,0,0,0]
			},
			"leg3": {
				"pos": [-9,3,2.5],
				"rot": [1,0,0,0]
			},
			"leg4": {
				"pos": [-3,9,2.5],
				"rot": [1,0,0,0]
			},
			"leg5": {
				"pos": [3,9,2.5],
				"rot": [1,0,0,0]
			},
			"leg6": {
				"pos": [9,3,2.5],
				"rot": [1,0,0,0]
			},
			"leg7": {
				"pos": [9.559362,-3.273865,4.534343],
				"rot": [0.988446,-0.037343,0.018392,0.145744]
			},
			"leg8": {
				"pos": [3.656567,-8.958758,2.942624],
				"rot": [0.997872,0.002673,0.036576,0.053904]
			}
		},
		{
			"ATTOVERCOG": {
				"pos": [0,-0,30],
				"rot": [1,0,0,0]
			},
			"head": {
				"pos": [0,0.516992,6.175534],
				"rot": [0.979138,-0.032403,0.033423,0.197791]
			},
			"leg1": {
				"pos": [-3,-9,2.5],
				"rot": [1,0,0,0]
			},
			"leg2": {
				"pos": [-9,-3,2.5],
				"rot": [1,0,0,0]
			},
			"leg3": {
				"pos": [-9,3,2.5],
				"rot": [1,0,0,0]
			},
			"leg4": {
				"pos": [-3,9,2.5],
				"rot": [1,0,0,0]
			},
			"leg5": {
				"pos": [3,9,2.5],
				"rot": [1,0,0,0]
			},
			"leg6": {
				"pos": [9,3,2.5],
				"rot": [1,0,0,0]
			},
			"leg7": {
				"pos": [9.634965,-3.325637,4.809303],
				"rot": [0.985102,-0.042787,0.020035,0.165354]
			},
			"leg8": {
				"pos": [3.628241,-8.914543,2.699341],
				"rot": [0.998568,0.000931,0.047667,0.024251]
			}
		},
		{
			"ATTOVERCOG": {
				"pos": [0,-0,30],
				"rot": [1,0,0,0]
			},
			"head": {
				"pos": [0,0.556294,6.192920],
				"rot": [0.975845,-0.035400,0.035431,0.212646]
			},
			"leg1": {
				"pos": [-3,-9,2.5],
				"rot": [1,0,0,0]
			},
			"leg2": {
				"pos": [-9,-3,2.5],
				"rot": [1,0,0,0]
			},
			"leg3": {
				"pos": [-9,3,2.5],
				"rot": [1,0,0,0]
			},
			"leg4": {
				"pos": [-3,9,2.5],
				"rot": [1,0,0,0]
			},
			"leg5": {
				"pos": [3,9,2.5],
				"rot": [1,0,0,0]
			},
			"leg6": {
				"pos": [9,3,2.5],
				"rot": [1,0,0,0]
			},
			"leg7": {
				"pos": [9.681463,-3.369330,4.978411],
				"rot": [0.982834,-0.046172,0.020942,0.177389]
			},
			"leg8": {
				"pos": [3.596063,-8.887348,2.549716],
				"rot": [0.998493,0.000190,0.054550,0.006043]
			}
		},
		{
			"ATTOVERCOG": {
				"pos": [0,-0,30],
				"rot": [1,0,0,0]
			},
			"head": {
				"pos": [0,0.593443,6.210435],
				"rot": [0.972511,-0.038294,0.037252,0.226646]
			},
			"leg1": {
				"pos": [-3,-9,2.5],
				"rot": [1,0,0,0]
			},
			"leg2": {
				"pos": [-9,-3,2.5],
				"rot": [1,0,0,0]
			},
			"leg3": {
				"pos": [-9,3,2.5],
				"rot": [1,0,0,0]
			},
			"leg4": {
				"pos": [-3,9,2.5],
				"rot": [1,0,0,0]
			},
			"leg5": {
				"pos": [3,9,2.5],
				"rot": [1,0,0,0]
			},
			"leg6": {
				"pos": [9,3,2.5],
				"rot": [1,0,0,0]
			},
			"leg7": {
				"pos": [9.696913,-3.403561,5.034601],
				"rot": [0.982045,-0.047303,0.021226,0.181383]
			},
			"leg8": {
				"pos": [3.560831,-8.878313,2.5],
				"rot": [0.998383,0,0.056845,0]
			}
		},
		{
			"ATTOVERCOG": {
				"pos": [0,-0,30],
				"rot": [1,0,0,0]
			},
			"head": {
				"pos": [0,0.628013,6.227962],
				"rot": [0.969216,-0.041039,0.038878,0.239634]
			},
			"leg1": {
				"pos": [-3,-9,2.5],
				"rot": [1,0,0,0]
			},
			"leg2": {
				"pos": [-9,-3,2.5],
				"rot": [1,0,0,0]
			},
			"leg3": {
				"pos": [-9,3,2.5],
				"rot": [1,0,0,0]
			},
			"leg4": {
				"pos": [-3,9,2.5],
				"rot": [1,0,0,0]
			},
			"leg5": {
				"pos": [3,9,2.5],
				"rot": [1,0,0,0]
			},
			"leg6": {
				"pos": [9,3.014595,2.538948],
				"rot": [0.999975,-0.002496,0.000400,0.006540]
			},
			"leg7": {
				"pos": [9.681462,-3.432900,4.978411],
				"rot": [0.982905,-0.044644,0.021218,0.177356]
			},
			"leg8": {
				"pos": [3.516920,-8.881010,2.5],
				"rot": [0.998454,0,0.055586,0]
			}
		},
		{
			"ATTOVERCOG": {
				"pos": [0,-0,30],
				"rot": [1,0,0,0]
			},
			"head": {
				"pos": [0,0.659636,6.245391],
				"rot": [0.966040,-0.043592,0.040307,0.251478]
			},
			"leg1": {
				"pos": [-3,-9,2.5],
				"rot": [1,0,0,0]
			},
			"leg2": {
				"pos": [-9,-3,2.5],
				"rot": [1,0,0,0]
			},
			"leg3": {
				"pos": [-9,3,2.5],
				"rot": [1,0,0,0]
			},
			"leg4": {
				"pos": [-3,9,2.5],
				"rot": [1,0,0,0]
			},
			"leg5": {
				"pos": [3,9,2.5],
				"rot": [1,0,0,0]
			},
			"leg6": {
				"pos": [9,3.058520,2.656167],
				"rot": [0.999605,-0.010036,0.001406,0.026230]
			},
			"leg7": {
				"pos": [9.634965,-3.461876,4.809303],
				"rot": [0.985350,-0.036645,0.021066,0.165225]
			},
			"leg8": {
				"pos": [3.458626,-8.889130,2.5],
				"rot": [0.998658,0,0.051797,0]
			}
		},
		{
			"ATTOVERCOG": {
				"pos": [0,-0,30],
				"rot": [1,0,0,0]
			},
			"head": {
				"pos": [0,0.688010,6.262621],
				"rot": [0.963059,-0.045917,0.041540,0.262074]
			},
			"leg1": {
				"pos": [-3,-9,2.5],
				"rot": [1,0,0,0]
			},
			"leg2": {
				"pos": [-9,-3,2.5],
				"rot": [1,0,0,0]
			},
			"leg3": {
				"pos": [-9,3,2.5],
				"rot": [1,0,0,0]
			},
			"leg4": {
				"pos": [-3,9,2.5],
				"rot": [1,0,0,0]
			},
			"leg5": {
				"pos": [3,9,2.5],
				"rot": [1,0,0,0]
			},
			"leg6": {
				"pos": [9,3.129940,2.846758],
				"rot": [0.998049,-0.022370,0.002407,0.058249]
			},
			"leg7": {
				"pos": [9.559362,-3.489718,4.534343],
				"rot": [0.988868,-0.023658,0.020408,0.145476]
			},
			"leg8": {
				"pos": [3.387834,-8.902331,2.5],
				"rot": [0.998958,0,0.045634,0]
			}
		},
		{
			"ATTOVERCOG": {
				"pos": [0,-0,30],
				"rot": [1,0,0,0]
			},
			"head": {
				"pos": [0,0.712895,6.279567],
				"rot": [0.960343,-0.047982,0.042584,0.271342]
			},
			"leg1": {
				"pos": [-3,-9,2.5],
				"rot": [1,0,0,0]
			},
			"leg2": {
				"pos": [-9,-3,2.5],
				"rot": [1,0,0,0]
			},
			"leg3": {
				"pos": [-9,3,2.5],
				"rot": [1,0,0,0]
			},
			"leg4": {
				"pos": [-3,9,2.5],
				"rot": [1,0,0,0]
			},
			"leg5": {
				"pos": [3,9,2.5],
				"rot": [1,0,0,0]
			},
			"leg6": {
				"pos": [9,3.223353,3.096041],
				"rot": [0.994229,-0.038584,0.002522,0.100066]
			},
			"leg7": {
				"pos": [9.460478,-3.515440,4.174708],
				"rot": [0.992619,-0.006733,0.018782,0.119621]
			},
			"leg8": {
				"pos": [3.308556,-8.919597,2.5],
				"rot": [0.999294,0,0.037571,0]
			}
		},
		{
			"ATTOVERCOG": {
				"pos": [0,-0,30],
				"rot": [1,0,0,0]
			},
			"head": {
				"pos": [0,0.734112,6.296152],
				"rot": [0.957951,-0.049761,0.043445,0.279224]
			},
			"leg1": {
				"pos": [-3,-9,2.5],
				"rot": [1,0,0,0]
			},
			"leg2": {
				"pos": [-9,-3,2.5],
				"rot": [1,0,0,0]
			},
			"leg3": {
				"pos": [-9,3,2.5],
				"rot": [1,0,0,0]
			},
			"leg4": {
				"pos": [-3,9,2.5],
				"rot": [1,0,0,0]
			},
			"leg5": {
				"pos": [3,9,2.5],
				"rot": [1,0,0,0]
			},
			"leg6": {
				"pos": [9,3.329175,3.378439],
				"rot": [0.987461,-0.056959,0.001012,0.147225]
			},
			"leg7": {
				"pos": [9.348457,-3.537980,3.767301],
				"rot": [0.995707,0.012309,0.015899,0.090347]
			},
			"leg8": {
				"pos": [3.226962,-8.939156,2.5],
				"rot": [0.999596,0,0.028434,0]
			}
		},
		{
			"ATTOVERCOG": {
				"pos": [0,-0,30],
				"rot": [1,0,0,0]
			},
			"head": {
				"pos": [0,0.751539,6.312315],
				"rot": [0.955935,-0.051234,0.044132,0.285683]
			},
			"leg1": {
				"pos": [-3,-9,2.5],
				"rot": [1,0,0,0]
			},
			"leg2": {
				"pos": [-9,-3,2.5],
				"rot": [1,0,0,0]
			},
			"leg3": {
				"pos": [-9,3,2.5],
				"rot": [1,0,0,0]
			},
			"leg4": {
				"pos": [-3,9,2.5],
				"rot": [1,0,0,0]
			},
			"leg5": {
				"pos": [3,9,2.5],
				"rot": [1,0,0,0]
			},
			"leg6": {
				"pos": [9,3.434997,3.660837],
				"rot": [0.978110,-0.075215,-0.002240,0.194009]
			},
			"leg7": {
				"pos": [9.236436,-3.556448,3.359893],
				"rot": [0.997571,0.031161,0.011922,0.061145]
			},
			"leg8": {
				"pos": [3.150438,-8.958716,2.5],
				"rot": [0.999814,0,0.019295,0]
			}
		},
		{
			"ATTOVERCOG": {
				"pos": [0,-0,30],
				"rot": [1,0,0,0]
			},
			"head": {
				"pos": [0,0.765100,6.328005],
				"rot": [0.954335,-0.052389,0.044655,0.290701]
			},
			"leg1": {
				"pos": [-3,-9,2.5],
				"rot": [1,0,0,0]
			},
			"leg2": {
				"pos": [-9,-3,2.5],
				"rot": [1,0,0,0]
			},
			"leg3": {
				"pos": [-9,3,2.5],
				"rot": [1,0,0,0]
			},
			"leg4": {
				"pos": [-3,9,2.5],
				"rot": [1,0,0,0]
			},
			"leg5": {
				"pos": [3,9,2.5],
				"rot": [1,0,0,0]
			},
			"leg6": {
				"pos": [9,3.528411,3.910120],
				"rot": [0.967724,-0.091127,-0.006550,0.234870]
			},
			"leg7": {
				"pos": [9.137550,-3.570364,3.000258],
				"rot": [0.998208,0.047598,0.007513,0.035473]
			},
			"leg8": {
				"pos": [3.085858,-8.975983,2.5],
				"rot": [0.999937,0,0.011225,0]
			}
		},
		{
			"ATTOVERCOG": {
				"pos": [0,-0,30],
				"rot": [1,0,0,0]
			},
			"head": {
				"pos": [0,0.774763,6.343181],
				"rot": [0.953176,-0.053215,0.045021,0.294272]
			},
			"leg1": {
				"pos": [-3,-9,2.5],
				"rot": [1,0,0,0]
			},
			"leg2": {
				"pos": [-9,-3,2.5],
				"rot": [1,0,0,0]
			},
			"leg3": {
				"pos": [-9,3,2.5],
				"rot": [1,0,0,0]
			},
			"leg4": {
				"pos": [-3,9,2.5],
				"rot": [1,0,0,0]
			},
			"leg5": {
				"pos": [3,9,2.5],
				"rot": [1,0,0,0]
			},
			"leg6": {
				"pos": [9,3.599830,4.100711],
				"rot": [0.958448,-0.103106,-0.010749,0.265766]
			},
			"leg7": {
				"pos": [9.061948,-3.579732,2.725298],
				"rot": [0.998064,0.060013,0.003580,0.015936]
			},
			"leg8": {
				"pos": [3.038066,-8.989183,2.5],
				"rot": [0.999987,0,0.005056,0]
			}
		},
		{
			"ATTOVERCOG": {
				"pos": [0,-0,30],
				"rot": [1,0,0,0]
			},
			"head": {
				"pos": [0,0.780534,6.357811],
				"rot": [0.952478,-0.053711,0.045237,0.296402]
			},
			"leg1": {
				"pos": [-3,-9,2.5],
				"rot": [1,0,0,0]
			},
			"leg2": {
				"pos": [-9,-3,2.5],
				"rot": [1,0,0,0]
			},
			"leg3": {
				"pos": [-9,3,2.5],
				"rot": [1,0,0,0]
			},
			"leg4": {
				"pos": [-3,9,2.5],
				"rot": [1,0,0,0]
			},
			"leg5": {
				"pos": [3,9,2.5],
				"rot": [1,0,0,0]
			},
			"leg6": {
				"pos": [9,3.643755,4.217930],
				"rot": [0.952174,-0.110373,-0.013716,0.284596]
			},
			"leg7": {
				"pos": [9.015450,-3.584932,2.556190],
				"rot": [0.997706,0.067574,0.000923,0.003968]
			},
			"leg8": {
				"pos": [3.009372,-8.997302,2.5],
				"rot": [0.999999,0,0.001261,0]
			}
		},
		{
			"ATTOVERCOG": {
				"pos": [0,-0,30],
				"rot": [1,0,0,0]
			},
			"head": {
				"pos": [0,0.782446,6.371874],
				"rot": [0.952246,-0.053875,0.045308,0.297108]
			},
			"leg1": {
				"pos": [-3,-9,2.5],
				"rot": [1,0,0,0]
			},
			"leg2": {
				"pos": [-9,-3,2.5],
				"rot": [1,0,0,0]
			},
			"leg3": {
				"pos": [-9,3,2.5],
				"rot": [1,0,0,0]
			},
			"leg4": {
				"pos": [-3,9,2.5],
				"rot": [1,0,0,0]
			},
			"leg5": {
				"pos": [3,9,2.5],
				"rot": [1,0,0,0]
			},
			"leg6": {
				"pos": [9,3.658350,4.256878],
				"rot": [0.949994,-0.112769,-0.014767,0.290822]
			},
			"leg7": {
				"pos": [9,-3.586529,2.5],
				"rot": [0.997542,0.070074,0,0]
			},
			"leg8": {
				"pos": [3,-9,2.5],
				"rot": [1,0,0,0]
			}
		},
		{
			"ATTOVERCOG": {
				"pos": [0,-0,30],
				"rot": [1,0,0,0]
			},
			"head": {
				"pos": [0,0.780534,6.386140],
				"rot": [0.952636,-0.053813,0.045370,0.295856]
			},
			"leg1": {
				"pos": [-3,-9,2.5],
				"rot": [1,0,0,0]
			},
			"leg2": {
				"pos": [-9,-3,2.5],
				"rot": [1,0,0,0]
			},
			"leg3": {
				"pos": [-9,3,2.5],
				"rot": [1,0,0,0]
			},
			"leg4": {
				"pos": [-3,9,2.5],
				"rot": [1,0,0,0]
			},
			"leg5": {
				"pos": [3.026506,9.027055,2.561839],
				"rot": [0.999988,0.000102,-0.000769,0.004799]
			},
			"leg6": {
				"pos": [9,3.657208,4.217929],
				"rot": [0.952050,-0.111431,-0.014033,0.284581]
			},
			"leg7": {
				"pos": [9,-3.573526,2.5],
				"rot": [0.997650,0.068523,0,0]
			},
			"leg8": {
				"pos": [3,-9,2.5],
				"rot": [1,0,0,0]
			}
		},
		{
			"ATTOVERCOG": {
				"pos": [0,-0,30],
				"rot": [1,0,0,0]
			},
			"head": {
				"pos": [0,0.774763,6.401380],
				"rot": [0.953804,-0.053623,0.045555,0.292075]
			},
			"leg1": {
				"pos": [-3,-9,2.5],
				"rot": [1,0,0,0]
			},
			"leg2": {
				"pos": [-9,-3,2.5],
				"rot": [1,0,0,0]
			},
			"leg3": {
				"pos": [-9,3,2.5],
				"rot": [1,0,0,0]
			},
			"leg4": {
				"pos": [-3,9,2.5],
				"rot": [1,0,0,0]
			},
			"leg5": {
				"pos": [3.106280,9.108478,2.747947],
				"rot": [0.999810,0.000454,-0.003082,0.019242]
			},
			"leg6": {
				"pos": [9,3.653331,4.100711],
				"rot": [0.957987,-0.107302,-0.011913,0.265716]
			},
			"leg7": {
				"pos": [9,-3.534393,2.5],
				"rot": [0.997959,0.063854,0,0]
			},
			"leg8": {
				"pos": [3,-9,2.5],
				"rot": [1,0,0,0]
			}
		},
		{
			"ATTOVERCOG": {
				"pos": [0,-0,30],
				"rot": [1,0,0,0]
			},
			"head": {
				"pos": [0,0.765100,6.417576],
				"rot": [0.955726,-0.053302,0.045862,0.285733]
			},
			"leg1": {
				"pos": [-3,-9,2.5],
				"rot": [1,0,0,0]
			},
			"leg2": {
				"pos": [-9,-3,2.5],
				"rot": [1,0,0,0]
			},
			"leg3": {
				"pos": [-9,3,2.5],
				"rot": [1,0,0,0]
			},
			"leg4": {
				"pos": [-3,9,2.5],
				"rot": [1,0,0,0]
			},
			"leg5": {
				"pos": [3.235987,9.240867,3.050550],
				"rot": [0.999063,0.001169,-0.006834,0.042718]
			},
			"leg6": {
				"pos": [9,3.646000,3.910120],
				"rot": [0.966812,-0.100334,-0.008785,0.234797]
			},
			"leg7": {
				"pos": [9,-3.470765,2.5],
				"rot": [0.998416,0.056259,0,0]
			},
			"leg8": {
				"pos": [3,-9,2.5],
				"rot": [1,0,0,0]
			}
		},
		{
			"ATTOVERCOG": {
				"pos": [0,-0,30],
				"rot": [1,0,0,0]
			},
			"head": {
				"pos": [0,0.751539,6.434699],
				"rot": [0.958353,-0.052846,0.046287,0.276812]
			},
			"leg1": {
				"pos": [-3,-9,2.5],
				"rot": [1,0,0,0]
			},
			"leg2": {
				"pos": [-9,-3,2.5],
				"rot": [1,0,0,0]
			},
			"leg3": {
				"pos": [-9,3,2.5],
				"rot": [1,0,0,0]
			},
			"leg4": {
				"pos": [-3,9,2.5],
				"rot": [1,0,0,0]
			},
			"leg5": {
				"pos": [3.405637,9.414025,3.446338],
				"rot": [0.997232,0.002371,-0.011717,0.073388]
			},
			"leg6": {
				"pos": [9,3.634546,3.660836],
				"rot": [0.976788,-0.090777,-0.005328,0.193948]
			},
			"leg7": {
				"pos": [9,-3.387542,2.5],
				"rot": [0.998927,0.046322,0,0]
			},
			"leg8": {
				"pos": [3,-9,2.5],
				"rot": [1,0,0,0]
			}
		},
		{
			"ATTOVERCOG": {
				"pos": [0,-0,30],
				"rot": [1,0,0,0]
			},
			"head": {
				"pos": [0,0.734113,6.452704],
				"rot": [0.961607,-0.052251,0.046821,0.265312]
			},
			"leg1": {
				"pos": [-3,-9,2.5],
				"rot": [1,0,0,0]
			},
			"leg2": {
				"pos": [-9,-3,2.5],
				"rot": [1,0,0,0]
			},
			"leg3": {
				"pos": [-9,3,2.5],
				"rot": [1,0,0,0]
			},
			"leg4": {
				"pos": [-3,9,2.5],
				"rot": [1,0,0,0]
			},
			"leg5": {
				"pos": [3.597824,9.610187,3.894703],
				"rot": [0.993988,0.004101,-0.017205,0.108048]
			},
			"leg6": {
				"pos": [9,3.618536,3.378439],
				"rot": [0.985918,-0.079313,-0.002323,0.147210]
			},
			"leg7": {
				"pos": [9,-3.293264,2.5],
				"rot": [0.999385,0.035058,0,0]
			},
			"leg8": {
				"pos": [3,-9,2.5],
				"rot": [1,0,0,0]
			}
		},
		{
			"ATTOVERCOG": {
				"pos": [0,-0,30],
				"rot": [1,0,0,0]
			},
			"head": {
				"pos": [0,0.712895,6.471532],
				"rot": [0.965383,-0.051514,0.047456,0.251259]
			},
			"leg1": {
				"pos": [-3,-9,2.5],
				"rot": [1,0,0,0]
			},
			"leg2": {
				"pos": [-9,-3,2.5],
				"rot": [1,0,0,0]
			},
			"leg3": {
				"pos": [-9,3,2.5],
				"rot": [1,0,0,0]
			},
			"leg4": {
				"pos": [-3,9,2.5],
				"rot": [1,0,0,0]
			},
			"leg5": {
				"pos": [3.790010,9.806347,4.343068],
				"rot": [0.989505,0.006222,-0.022644,0.142574]
			},
			"leg6": {
				"pos": [9,3.597955,3.096041],
				"rot": [0.992719,-0.067008,-0.000341,0.100097]
			},
			"leg7": {
				"pos": [9,-3.198987,2.5],
				"rot": [0.999717,0.023791,0,0]
			},
			"leg8": {
				"pos": [3,-9,2.5],
				"rot": [1,0,0,0]
			}
		},
		{
			"ATTOVERCOG": {
				"pos": [0,-0,30],
				"rot": [1,0,0,0]
			},
			"head": {
				"pos": [0,0.688010,6.491107],
				"rot": [0.969550,-0.050634,0.048178,0.234708]
			},
			"leg1": {
				"pos": [-3,-9,2.5],
				"rot": [1,0,0,0]
			},
			"leg2": {
				"pos": [-9,-3,2.5],
				"rot": [1,0,0,0]
			},
			"leg3": {
				"pos": [-9,3,2.5],
				"rot": [1,0,0,0]
			},
			"leg4": {
				"pos": [-3,9,2.5],
				"rot": [1,0,0,0]
			},
			"leg5": {
				"pos": [3.959661,9.979506,4.738857],
				"rot": [0.984520,0.008428,-0.027427,0.172905]
			},
			"leg6": {
				"pos": [9,3.573250,2.846758],
				"rot": [0.996781,-0.055035,0.000498,0.058297]
			},
			"leg7": {
				"pos": [9,-3.115764,2.5],
				"rot": [0.999904,0.013841,0,0]
			},
			"leg8": {
				"pos": [3,-9,2.5],
				"rot": [1,0,0,0]
			}
		},
		{
			"ATTOVERCOG": {
				"pos": [0,-0,30],
				"rot": [1,0,0,0]
			},
			"head": {
				"pos": [0,0.659636,6.511336],
				"rot": [0.973957,-0.049611,0.048971,0.215752]
			},
			"leg1": {
				"pos": [-3,-9,2.5],
				"rot": [1,0,0,0]
			},
			"leg2": {
				"pos": [-9,-3,2.5],
				"rot": [1,0,0,0]
			},
			"leg3": {
				"pos": [-9,3,2.5],
				"rot": [1,0,0,0]
			},
			"leg4": {
				"pos": [-3,9,2.5],
				"rot": [1,0,0,0]
			},
			"leg5": {
				"pos": [4.089367,10.111896,5.041458],
				"rot": [0.980059,0.010342,-0.031135,0.195980]
			},
			"leg6": {
				"pos": [9,3.545183,2.656167],
				"rot": [0.998671,-0.044353,0.000504,0.026263]
			},
			"leg7": {
				"pos": [9,-3.052136,2.5],
				"rot": [0.999981,0.006234,0,0]
			},
			"leg8": {
				"pos": [3,-9,2.5],
				"rot": [1,0,0,0]
			}
		},
		{
			"ATTOVERCOG": {
				"pos": [0,-0,30],
				"rot": [1,0,0,0]
			},
			"head": {
				"pos": [0,0.628013,6.532105],
				"rot": [0.978433,-0.048447,0.049818,0.194527]
			},
			"leg1": {
				"pos": [-3,-9,2.5],
				"rot": [1,0,0,0]
			},
			"leg2": {
				"pos": [-9,-3,2.5],
				"rot": [1,0,0,0]
			},
			"leg3": {
				"pos": [-9,3,2.5],
				"rot": [1,0,0,0]
			},
			"leg4": {
				"pos": [-3,9,2.5],
				"rot": [1,0,0,0]
			},
			"leg5": {
				"pos": [4.169141,10.193317,5.227567],
				"rot": [0.977031,0.011648,-0.033566,0.210116]
			},
			"leg6": {
				"pos": [9,3.514618,2.538948],
				"rot": [0.999347,-0.035541,0.000183,0.006549]
			},
			"leg7": {
				"pos": [9,-3.013003,2.5],
				"rot": [0.999999,0.001555,0,0]
			},
			"leg8": {
				"pos": [3,-9,2.5],
				"rot": [1,0,0,0]
			}
		},
		{
			"ATTOVERCOG": {
				"pos": [0,-0,30],
				"rot": [1,0,0,0]
			},
			"head": {
				"pos": [0,0.593444,6.553286],
				"rot": [0.982798,-0.047147,0.050696,0.171218]
			},
			"leg1": {
				"pos": [-3,-9,2.5],
				"rot": [1,0,0,0]
			},
			"leg2": {
				"pos": [-9,-3,2.5],
				"rot": [1,0,0,0]
			},
			"leg3": {
				"pos": [-9,3,2.5],
				"rot": [1,0,0,0]
			},
			"leg4": {
				"pos": [-3,9,2.5],
				"rot": [1,0,0,0]
			},
			"leg5": {
				"pos": [4.195647,10.220372,5.289406],
				"rot": [0.975966,0.012167,-0.034679,0.214801]
			},
			"leg6": {
				"pos": [9,3.482337,2.5],
				"rot": [0.999584,-0.028842,0,0]
			},
			"leg7": {
				"pos": [9,-3,2.5],
				"rot": [1,0,0,0]
			},
			"leg8": {
				"pos": [3,-9,2.5],
				"rot": [1,0,0,0]
			}
		},
		{
			"ATTOVERCOG": {
				"pos": [0,-0,30],
				"rot": [1,0,0,0]
			},
			"head": {
				"pos": [0,0.556294,6.574727],
				"rot": [0.986871,-0.045720,0.051584,0.146060]
			},
			"leg1": {
				"pos": [-3,-9,2.5],
				"rot": [1,0,0,0]
			},
			"leg2": {
				"pos": [-9,-3,2.5],
				"rot": [1,0,0,0]
			},
			"leg3": {
				"pos": [-9,3,2.5],
				"rot": [1,0,0,0]
			},
			"leg4": {
				"pos": [-3.017687,9.011961,2.555278],
				"rot": [0.999979,-0.000952,0.001663,-0.006283]
			},
			"leg5": {
				"pos": [4.185257,10.193317,5.227567],
				"rot": [0.977151,0.011863,-0.035233,0.209270]
			},
			"leg6": {
				"pos": [9,3.443264,2.5],
				"rot": [0.999727,-0.023357,0,0]
			},
			"leg7": {
				"pos": [9,-3,2.5],
				"rot": [1,0,0,0]
			},
			"leg8": {
				"pos": [3,-9,2.5],
				"rot": [1,0,0,0]
			}
		},
		{
			"ATTOVERCOG": {
				"pos": [0,-0,30],
				"rot": [1,0,0,0]
			},
			"head": {
				"pos": [0,0.516992,6.596266],
				"rot": [0.990482,-0.044179,0.052457,0.119339]
			},
			"leg1": {
				"pos": [-3,-9,2.5],
				"rot": [1,0,0,0]
			},
			"leg2": {
				"pos": [-9,-3,2.5],
				"rot": [1,0,0,0]
			},
			"leg3": {
				"pos": [-9,3,2.5],
				"rot": [1,0,0,0]
			},
			"leg4": {
				"pos": [-3.070919,9.047960,2.721642],
				"rot": [0.999654,-0.003692,0.006739,-0.025171]
			},
			"leg5": {
				"pos": [4.153191,10.111895,5.041459],
				"rot": [0.980563,0.010729,-0.035938,0.192586]
			},
			"leg6": {
				"pos": [9,3.392261,2.5],
				"rot": [0.999834,-0.018218,0,0]
			},
			"leg7": {
				"pos": [9,-3,2.5],
				"rot": [1,0,0,0]
			},
			"leg8": {
				"pos": [3,-9,2.5],
				"rot": [1,0,0,0]
			}
		},
		{
			"ATTOVERCOG": {
				"pos": [0,-0,30],
				"rot": [1,0,0,0]
			},
			"head": {
				"pos": [0,0.476021,6.617723],
				"rot": [0.993478,-0.042541,0.053291,0.091387]
			},
			"leg1": {
				"pos": [-3,-9,2.5],
				"rot": [1,0,0,0]
			},
			"leg2": {
				"pos": [-9,-3,2.5],
				"rot": [1,0,0,0]
			},
			"leg3": {
				"pos": [-9,3,2.5],
				"rot": [1,0,0,0]
			},
			"leg4": {
				"pos": [-3.157470,9.106493,2.992141],
				"rot": [0.998297,-0.007732,0.015209,-0.055792]
			},
			"leg5": {
				"pos": [4.099188,9.979506,4.738857],
				"rot": [0.985513,0.008789,-0.036716,0.165343]
			},
			"leg6": {
				"pos": [9,3.330964,2.5],
				"rot": [0.999908,-0.013557,0,0]
			},
			"leg7": {
				"pos": [9,-3,2.5],
				"rot": [1,0,0,0]
			},
			"leg8": {
				"pos": [3,-9,2.5],
				"rot": [1,0,0,0]
			}
		},
		{
			"ATTOVERCOG": {
				"pos": [0,-0,30],
				"rot": [1,0,0,0]
			},
			"head": {
				"pos": [0,0.433911,6.638914],
				"rot": [0.995738,-0.040824,0.054062,0.062579]
			},
			"leg1": {
				"pos": [-3,-9,2.5],
				"rot": [1,0,0,0]
			},
			"leg2": {
				"pos": [-9,-3,2.5],
				"rot": [1,0,0,0]
			},
			"leg3": {
				"pos": [-9,3,2.5],
				"rot": [1,0,0,0]
			},
			"leg4": {
				"pos": [-3.270675,9.183051,3.345941],
				"rot": [0.994986,-0.012226,0.026651,-0.095620]
			},
			"leg5": {
				"pos": [4.025166,9.806347,4.343067],
				"rot": [0.990850,0.006178,-0.037439,0.129523]
			},
			"leg6": {
				"pos": [9,3.262794,2.5],
				"rot": [0.999955,-0.009511,0,0]
			},
			"leg7": {
				"pos": [9,-3,2.5],
				"rot": [1,0,0,0]
			},
			"leg8": {
				"pos": [3,-9,2.5],
				"rot": [1,0,0,0]
			}
		},
		{
			"ATTOVERCOG": {
				"pos": [0,-0,30],
				"rot": [1,0,0,0]
			},
			"head": {
				"pos": [0,0.391223,6.659650],
				"rot": [0.997180,-0.039053,0.054749,0.033318]
			},
			"leg1": {
				"pos": [-3,-9,2.5],
				"rot": [1,0,0,0]
			},
			"leg2": {
				"pos": [-9,-3,2.5],
				"rot": [1,0,0,0]
			},
			"leg3": {
				"pos": [-9,3,2.5],
				"rot": [1,0,0,0]
			},
			"leg4": {
				"pos": [-3.398918,9.269779,3.746738],
				"rot": [0.989160,-0.016203,0.040048,-0.140342]
			},
			"leg5": {
				"pos": [3.935800,9.610186,3.894703],
				"rot": [0.995325,0.003164,-0.037980,0.088741]
			},
			"leg6": {
				"pos": [9,3.192976,2.5],
				"rot": [0.999981,-0.006191,0,0]
			},
			"leg7": {
				"pos": [9,-3,2.5],
				"rot": [1,0,0,0]
			},
			"leg8": {
				"pos": [3,-9,2.5],
				"rot": [1,0,0,0]
			}
		},
		{
			"ATTOVERCOG": {
				"pos": [0,-0,30],
				"rot": [1,0,0,0]
			},
			"head": {
				"pos": [0,0.348534,6.679744],
				"rot": [0.997765,-0.037253,0.055334,0.004023]
			},
			"leg1": {
				"pos": [-3,-9,2.5],
				"rot": [1,0,0,0]
			},
			"leg2": {
				"pos": [-9,-3,2.5],
				"rot": [1,0,0,0]
			},
			"leg3": {
				"pos": [-9,3,2.5],
				"rot": [1,0,0,0]
			},
			"leg4": {
				"pos": [-3.527161,9.356507,4.147535],
				"rot": [0.981168,-0.018965,0.053823,-0.184532]
			},
			"leg5": {
				"pos": [3.838133,9.414026,3.446338],
				"rot": [0.998123,0.000115,-0.038271,0.047809]
			},
			"leg6": {
				"pos": [9,3.127728,2.5],
				"rot": [0.999993,-0.003653,0,0]
			},
			"leg7": {
				"pos": [9,-3,2.5],
				"rot": [1,0,0,0]
			},
			"leg8": {
				"pos": [3,-9,2.5],
				"rot": [1,0,0,0]
			}
		},
		{
			"ATTOVERCOG": {
				"pos": [0,-0,30],
				"rot": [1,0,0,0]
			},
			"head": {
				"pos": [0,0.306424,6.699015],
				"rot": [0.997502,-0.035450,0.055800,-0.024884]
			},
			"leg1": {
				"pos": [-3,-9,2.5],
				"rot": [1,0,0,0]
			},
			"leg2": {
				"pos": [-9,-3,2.5],
				"rot": [1,0,0,0]
			},
			"leg3": {
				"pos": [-9,3,2.5],
				"rot": [1,0,0,0]
			},
			"leg4": {
				"pos": [-3.640366,9.433065,4.501336],
				"rot": [0.972351,-0.020373,0.066227,-0.223010]
			},
			"leg5": {
				"pos": [3.740044,9.240867,3.050549],
				"rot": [0.999194,-0.002590,-0.038334,0.011608]
			},
			"leg6": {
				"pos": [9,3.072809,2.5],
				"rot": [0.999998,-0.001869,0,0]
			},
			"leg7": {
				"pos": [9,-3,2.5],
				"rot": [1,0,0,0]
			},
			"leg8": {
				"pos": [3,-9,2.5],
				"rot": [1,0,0,0]
			}
		},
		{
			"ATTOVERCOG": {
				"pos": [0,-0,30],
				"rot": [1,0,0,0]
			},
			"head": {
				"pos": [0,0.265454,6.717298],
				"rot": [0.996447,-0.033672,0.056137,-0.052995]
			},
			"leg1": {
				"pos": [-3,-9,2.5],
				"rot": [1,0,0,0]
			},
			"leg2": {
				"pos": [-9,-3,2.5],
				"rot": [1,0,0,0]
			},
			"leg3": {
				"pos": [-9,3,2.5],
				"rot": [1,0,0,0]
			},
			"leg4": {
				"pos": [-3.726917,9.491597,4.771834],
				"rot": [0.964516,-0.020788,0.075824,-0.252045]
			},
			"leg5": {
				"pos": [3.648383,9.108478,2.747947],
				"rot": [0.999127,-0.004661,-0.038262,-0.016082]
			},
			"leg6": {
				"pos": [9,3.032248,2.5],
				"rot": [1,-0.000749,0,0]
			},
			"leg7": {
				"pos": [9,-3,2.5],
				"rot": [1,0,0,0]
			},
			"leg8": {
				"pos": [3,-9,2.5],
				"rot": [1,0,0,0]
			}
		},
		{
			"ATTOVERCOG": {
				"pos": [0,-0,30],
				"rot": [1,0,0,0]
			},
			"head": {
				"pos": [0,0.226152,6.734442],
				"rot": [0.994694,-0.031946,0.056337,-0.079929]
			},
			"leg1": {
				"pos": [-3,-9,2.5],
				"rot": [1,0,0,0]
			},
			"leg2": {
				"pos": [-9,-3,2.5],
				"rot": [1,0,0,0]
			},
			"leg3": {
				"pos": [-9,3,2.5],
				"rot": [1,0,0,0]
			},
			"leg4": {
				"pos": [-3.780149,9.527596,4.938199],
				"rot": [0.959236,-0.020756,0.081763,-0.269721]
			},
			"leg5": {
				"pos": [3.567848,9.027055,2.561839],
				"rot": [0.998705,-0.005932,-0.038167,-0.033107]
			},
			"leg6": {
				"pos": [9,3.007933,2.5],
				"rot": [1,-0.000168,0,0]
			},
			"leg7": {
				"pos": [9,-3,2.5],
				"rot": [1,0,0,0]
			},
			"leg8": {
				"pos": [3,-9,2.5],
				"rot": [1,0,0,0]
			}
		},
		{
			"ATTOVERCOG": {
				"pos": [0,-0,30],
				"rot": [1,0,0,0]
			},
			"head": {
				"pos": [0,0.189002,6.750319],
				"rot": [0.992373,-0.030295,0.056397,-0.105342]
			},
			"leg1": {
				"pos": [-3,-9,2.5],
				"rot": [1,0,0,0]
			},
			"leg2": {
				"pos": [-9,-3,2.5],
				"rot": [1,0,0,0]
			},
			"leg3": {
				"pos": [-9,3,2.5],
				"rot": [1,0,0,0]
			},
			"leg4": {
				"pos": [-3.797836,9.539558,4.993477],
				"rot": [0.957405,-0.020697,0.083741,-0.275563]
			},
			"leg5": {
				"pos": [3.500905,9,2.5],
				"rot": [0.998501,-0.006354,-0.038126,-0.038762]
			},
			"leg6": {
				"pos": [9,3,2.5],
				"rot": [1,0,0,0]
			},
			"leg7": {
				"pos": [9,-3,2.5],
				"rot": [1,0,0,0]
			},
			"leg8": {
				"pos": [3,-9,2.5],
				"rot": [1,0,0,0]
			}
		},
		{
			"ATTOVERCOG": {
				"pos": [0,-0,30],
				"rot": [1,0,0,0]
			},
			"head": {
				"pos": [0,0.154432,6.764822],
				"rot": [0.989635,-0.028740,0.056317,-0.128936]
			},
			"leg1": {
				"pos": [-3,-9,2.5],
				"rot": [1,0,0,0]
			},
			"leg2": {
				"pos": [-9,-3,2.5],
				"rot": [1,0,0,0]
			},
			"leg3": {
				"pos": [-9.013993,3.013705,2.538613],
				"rot": [0.999964,-0.001209,-0.002398,-0.008044]
			},
			"leg4": {
				"pos": [-3.793018,9.527597,4.938199],
				"rot": [0.958667,-0.020584,0.081807,-0.271740]
			},
			"leg5": {
				"pos": [3.438259,9,2.5],
				"rot": [0.998567,-0.006182,-0.037287,-0.037900]
			},
			"leg6": {
				"pos": [9,3,2.5],
				"rot": [1,0,0,0]
			},
			"leg7": {
				"pos": [9,-3,2.5],
				"rot": [1,0,0,0]
			},
			"leg8": {
				"pos": [3,-9,2.5],
				"rot": [1,0,0,0]
			}
		},
		{
			"ATTOVERCOG": {
				"pos": [0,-0,30],
				"rot": [1,0,0,0]
			},
			"head": {
				"pos": [0,0.122809,6.777868],
				"rot": [0.986645,-0.027300,0.056101,-0.150465]
			},
			"leg1": {
				"pos": [-3,-9,2.5],
				"rot": [1,0,0,0]
			},
			"leg2": {
				"pos": [-9,-3,2.5],
				"rot": [1,0,0,0]
			},
			"leg3": {
				"pos": [-9.056105,3.054949,2.654820],
				"rot": [0.999421,-0.005077,-0.009496,-0.032280]
			},
			"leg4": {
				"pos": [-3.777987,9.491598,4.771834],
				"rot": [0.962398,-0.020160,0.075994,-0.260018]
			},
			"leg5": {
				"pos": [3.370656,9,2.5],
				"rot": [0.998756,-0.005671,-0.034759,-0.035307]
			},
			"leg6": {
				"pos": [9,3,2.5],
				"rot": [1,0,0,0]
			},
			"leg7": {
				"pos": [9,-3,2.5],
				"rot": [1,0,0,0]
			},
			"leg8": {
				"pos": [3,-9,2.5],
				"rot": [1,0,0,0]
			}
		},
		{
			"ATTOVERCOG": {
				"pos": [0,-0,30],
				"rot": [1,0,0,0]
			},
			"head": {
				"pos": [0,0.094436,6.789396],
				"rot": [0.983569,-0.025989,0.055754,-0.169730]
			},
			"leg1": {
				"pos": [-3,-9,2.5],
				"rot": [1,0,0,0]
			},
			"leg2": {
				"pos": [-9,-3,2.5],
				"rot": [1,0,0,0]
			},
			"leg3": {
				"pos": [-9.124577,3.122011,2.843767],
				"rot": [0.997137,-0.012092,-0.020623,-0.071734]
			},
			"leg4": {
				"pos": [-3.752303,9.433065,4.501336],
				"rot": [0.968198,-0.019183,0.066581,-0.240400]
			},
			"leg5": {
				"pos": [3.300024,9,2.5],
				"rot": [0.999035,-0.004868,-0.030642,-0.031093]
			},
			"leg6": {
				"pos": [9,3,2.5],
				"rot": [1,0,0,0]
			},
			"leg7": {
				"pos": [9,-3,2.5],
				"rot": [1,0,0,0]
			},
			"leg8": {
				"pos": [3,-9,2.5],
				"rot": [1,0,0,0]
			}
		},
		{
			"ATTOVERCOG": {
				"pos": [0,-0,30],
				"rot": [1,0,0,0]
			},
			"head": {
				"pos": [0,0.069551,6.799366],
				"rot": [0.980568,-0.024815,0.055284,-0.186585]
			},
			"leg1": {
				"pos": [-3,-9,2.5],
				"rot": [1,0,0,0]
			},
			"leg2": {
				"pos": [-9,-3,2.5],
				"rot": [1,0,0,0]
			},
			"leg3": {
				"pos": [-9.214134,3.209725,3.090901],
				"rot": [0.991518,-0.022570,-0.034324,-0.123307]
			},
			"leg4": {
				"pos": [-3.716448,9.356507,4.147536],
				"rot": [0.975226,-0.017351,0.054364,-0.213723]
			},
			"leg5": {
				"pos": [3.229438,9,2.5],
				"rot": [0.999346,-0.003870,-0.025248,-0.025584]
			},
			"leg6": {
				"pos": [9,3,2.5],
				"rot": [1,0,0,0]
			},
			"leg7": {
				"pos": [9,-3,2.5],
				"rot": [1,0,0,0]
			},
			"leg8": {
				"pos": [3,-9,2.5],
				"rot": [1,0,0,0]
			}
		},
		{
			"ATTOVERCOG": {
				"pos": [0,-0,30],
				"rot": [1,0,0,0]
			},
			"head": {
				"pos": [0,0.048333,6.807760],
				"rot": [0.977789,-0.023787,0.054699,-0.200924]
			},
			"leg1": {
				"pos": [-3,-9,2.5],
				"rot": [1,0,0,0]
			},
			"leg2": {
				"pos": [-9,-3,2.5],
				"rot": [1,0,0,0]
			},
			"leg3": {
				"pos": [-9.315589,3.309090,3.370863],
				"rot": [0.981534,-0.036128,-0.048542,-0.181466]
			},
			"leg4": {
				"pos": [-3.672153,9.269779,3.746738],
				"rot": [0.982359,-0.014499,0.040696,-0.181949]
			},
			"leg5": {
				"pos": [3.162928,9,2.5],
				"rot": [0.999626,-0.002810,-0.019125,-0.019349]
			},
			"leg6": {
				"pos": [9,3,2.5],
				"rot": [1,0,0,0]
			},
			"leg7": {
				"pos": [9,-3,2.5],
				"rot": [1,0,0,0]
			},
			"leg8": {
				"pos": [3,-9,2.5],
				"rot": [1,0,0,0]
			}
		},
		{
			"ATTOVERCOG": {
				"pos": [0,-0,30],
				"rot": [1,0,0,0]
			},
			"head": {
				"pos": [0,0.030907,6.814574],
				"rot": [0.975359,-0.022905,0.054006,-0.212683]
			},
			"leg1": {
				"pos": [-3,-9,2.5],
				"rot": [1,0,0,0]
			},
			"leg2": {
				"pos": [-9,-3,2.5],
				"rot": [1,0,0,0]
			},
			"leg3": {
				"pos": [-9.417044,3.408456,3.650825],
				"rot": [0.967706,-0.051347,-0.061222,-0.239081]
			},
			"leg4": {
				"pos": [-3.622319,9.183051,3.345941],
				"rot": [0.988546,-0.010801,0.027260,-0.148045]
			},
			"leg5": {
				"pos": [3.104720,9,2.5],
				"rot": [0.999828,-0.001826,-0.012989,-0.013120]
			},
			"leg6": {
				"pos": [9,3,2.5],
				"rot": [1,0,0,0]
			},
			"leg7": {
				"pos": [9,-3,2.5],
				"rot": [1,0,0,0]
			},
			"leg8": {
				"pos": [3,-9,2.5],
				"rot": [1,0,0,0]
			}
		},
		{
			"ATTOVERCOG": {
				"pos": [0,-0,30],
				"rot": [1,0,0,0]
			},
			"head": {
				"pos": [0,0.017346,6.819820],
				"rot": [0.973380,-0.022168,0.053215,-0.221828]
			},
			"leg1": {
				"pos": [-3,-9,2.5],
				"rot": [1,0,0,0]
			},
			"leg2": {
				"pos": [-9,-3,2.5],
				"rot": [1,0,0,0]
			},
			"leg3": {
				"pos": [-9.506602,3.496169,3.897959],
				"rot": [0.952323,-0.066045,-0.071020,-0.289265]
			},
			"leg4": {
				"pos": [-3.570405,9.106493,2.992141],
				"rot": [0.993179,-0.006810,0.015643,-0.115347]
			},
			"leg5": {
				"pos": [3.058201,9,2.5],
				"rot": [0.999942,-0.001021,-0.007562,-0.007628]
			},
			"leg6": {
				"pos": [9,3,2.5],
				"rot": [1,0,0,0]
			},
			"leg7": {
				"pos": [9,-3,2.5],
				"rot": [1,0,0,0]
			},
			"leg8": {
				"pos": [3,-9,2.5],
				"rot": [1,0,0,0]
			}
		},
		{
			"ATTOVERCOG": {
				"pos": [0,-0,30],
				"rot": [1,0,0,0]
			},
			"head": {
				"pos": [0,0.007682,6.823522],
				"rot": [0.971931,-0.021574,0.052333,-0.228353]
			},
			"leg1": {
				"pos": [-3,-9,2.5],
				"rot": [1,0,0,0]
			},
			"leg2": {
				"pos": [-9,-3,2.5],
				"rot": [1,0,0,0]
			},
			"leg3": {
				"pos": [-9.575073,3.563231,4.086905],
				"rot": [0.938570,-0.078010,-0.077567,-0.327084]
			},
			"leg4": {
				"pos": [-3.519592,9.047961,2.721642],
				"rot": [0.996203,-0.003269,0.006954,-0.086720]
			},
			"leg5": {
				"pos": [3.025227,9,2.5],
				"rot": [0.999988,-0.000446,-0.003408,-0.003434]
			},
			"leg6": {
				"pos": [9,3,2.5],
				"rot": [1,0,0,0]
			},
			"leg7": {
				"pos": [9,-3,2.5],
				"rot": [1,0,0,0]
			},
			"leg8": {
				"pos": [3,-9,2.5],
				"rot": [1,0,0,0]
			}
		},
		{
			"ATTOVERCOG": {
				"pos": [0,-0,30],
				"rot": [1,0,0,0]
			},
			"head": {
				"pos": [0,0.001912,6.825713],
				"rot": [0.971064,-0.021116,0.051368,-0.232273]
			},
			"leg1": {
				"pos": [-3,-9,2.5],
				"rot": [1,0,0,0]
			},
			"leg2": {
				"pos": [-9,-3,2.5],
				"rot": [1,0,0,0]
			},
			"leg3": {
				"pos": [-9.617186,3.604476,4.203114],
				"rot": [0.929263,-0.085657,-0.081168,-0.350065]
			},
			"leg4": {
				"pos": [-3.472219,9.011962,2.555278],
				"rot": [0.997945,-0.000855,0.001715,-0.064051]
			},
			"leg5": {
				"pos": [3.006093,9,2.5],
				"rot": [0.999999,-0.000109,-0.000850,-0.000856]
			},
			"leg6": {
				"pos": [9,3,2.5],
				"rot": [1,0,0,0]
			},
			"leg7": {
				"pos": [9,-3,2.5],
				"rot": [1,0,0,0]
			},
			"leg8": {
				"pos": [3,-9,2.5],
				"rot": [1,0,0,0]
			}
		},
		{
			"ATTOVERCOG": {
				"pos": [0,-0,30],
				"rot": [1,0,0,0]
			},
			"head": {
				"pos": [0,-0,6.826433],
				"rot": [0.970803,-0.020786,0.050325,-0.233615]
			},
			"leg1": {
				"pos": [-3,-9,2.5],
				"rot": [1,0,0,0]
			},
			"leg2": {
				"pos": [-9,-3,2.5],
				"rot": [1,0,0,0]
			},
			"leg3": {
				"pos": [-9.631179,3.618181,4.241726],
				"rot": [0.926028,-0.088244,-0.082292,-0.357650]
			},
			"leg4": {
				"pos": [-3.429664,9,2.5],
				"rot": [0.998837,0,0,-0.048212]
			},
			"leg5": {
				"pos": [3,9,2.5],
				"rot": [1,0,0,0]
			},
			"leg6": {
				"pos": [9,3,2.5],
				"rot": [1,0,0,0]
			},
			"leg7": {
				"pos": [9,-3,2.5],
				"rot": [1,0,0,0]
			},
			"leg8": {
				"pos": [3,-9,2.5],
				"rot": [1,0,0,0]
			}
		},
		{
			"ATTOVERCOG": {
				"pos": [0,-0,30],
				"rot": [1,0,0,0]
			},
			"head": {
				"pos": [0,-0,6.824414],
				"rot": [0.970987,-0.020507,0.049159,-0.233123]
			},
			"leg1": {
				"pos": [-3,-9,2.5],
				"rot": [1,0,0,0]
			},
			"leg2": {
				"pos": [-9,-3.013004,2.546534],
				"rot": [0.999989,-0.000940,-0.001129,-0.004458]
			},
			"leg3": {
				"pos": [-9.610285,3.613320,4.203114],
				"rot": [0.928690,-0.085261,-0.081847,-0.351520]
			},
			"leg4": {
				"pos": [-3.385746,9,2.5],
				"rot": [0.999334,0,0,-0.036502]
			},
			"leg5": {
				"pos": [3,9,2.5],
				"rot": [1,0,0,0]
			},
			"leg6": {
				"pos": [9,3,2.5],
				"rot": [1,0,0,0]
			},
			"leg7": {
				"pos": [9,-3,2.5],
				"rot": [1,0,0,0]
			},
			"leg8": {
				"pos": [3,-9,2.5],
				"rot": [1,0,0,0]
			}
		},
		{
			"ATTOVERCOG": {
				"pos": [0,-0,30],
				"rot": [1,0,0,0]
			},
			"head": {
				"pos": [0,-0,6.818319],
				"rot": [0.971448,-0.020205,0.047822,-0.231502]
			},
			"leg1": {
				"pos": [-3,-9,2.5],
				"rot": [1,0,0,0]
			},
			"leg2": {
				"pos": [-9,-3.052140,2.686581],
				"rot": [0.999823,-0.003830,-0.004475,-0.017885]
			},
			"leg3": {
				"pos": [-9.547402,3.598281,4.086905],
				"rot": [0.936450,-0.076309,-0.080263,-0.332861]
			},
			"leg4": {
				"pos": [-3.334270,9,2.5],
				"rot": [0.999656,0,0,-0.026226]
			},
			"leg5": {
				"pos": [3,9,2.5],
				"rot": [1,0,0,0]
			},
			"leg6": {
				"pos": [9,3,2.5],
				"rot": [1,0,0,0]
			},
			"leg7": {
				"pos": [9,-3,2.5],
				"rot": [1,0,0,0]
			},
			"leg8": {
				"pos": [3,-9,2.5],
				"rot": [1,0,0,0]
			}
		},
		{
			"ATTOVERCOG": {
				"pos": [0,-0,30],
				"rot": [1,0,0,0]
			},
			"head": {
				"pos": [0,-0,6.808112],
				"rot": [0.972182,-0.019875,0.046314,-0.228739]
			},
			"leg1": {
				"pos": [-3,-9,2.5],
				"rot": [1,0,0,0]
			},
			"leg2": {
				"pos": [-9,-3.115773,2.914290],
				"rot": [0.999124,-0.008720,-0.009749,-0.039747]
			},
			"leg3": {
				"pos": [-9.445159,3.572863,3.897959],
				"rot": [0.948191,-0.061884,-0.076919,-0.301973]
			},
			"leg4": {
				"pos": [-3.276786,9,2.5],
				"rot": [0.999845,0,0,-0.017629]
			},
			"leg5": {
				"pos": [3,9,2.5],
				"rot": [1,0,0,0]
			},
			"leg6": {
				"pos": [9,3,2.5],
				"rot": [1,0,0,0]
			},
			"leg7": {
				"pos": [9,-3,2.5],
				"rot": [1,0,0,0]
			},
			"leg8": {
				"pos": [3,-9,2.5],
				"rot": [1,0,0,0]
			}
		},
		{
			"ATTOVERCOG": {
				"pos": [0,-0,30],
				"rot": [1,0,0,0]
			},
			"head": {
				"pos": [0,-0,6.793788],
				"rot": [0.973179,-0.019510,0.044641,-0.224829]
			},
			"leg1": {
				"pos": [-3,-9,2.5],
				"rot": [1,0,0,0]
			},
			"leg2": {
				"pos": [-9,-3.199002,3.212123],
				"rot": [0.997406,-0.015458,-0.016321,-0.068378]
			},
			"leg3": {
				"pos": [-9.311429,3.537866,3.650825],
				"rot": [0.961842,-0.043351,-0.071103,-0.260626]
			},
			"leg4": {
				"pos": [-3.216147,9,2.5],
				"rot": [0.999941,0,0,-0.010887]
			},
			"leg5": {
				"pos": [3,9,2.5],
				"rot": [1,0,0,0]
			},
			"leg6": {
				"pos": [9,3,2.5],
				"rot": [1,0,0,0]
			},
			"leg7": {
				"pos": [9,-3,2.5],
				"rot": [1,0,0,0]
			},
			"leg8": {
				"pos": [3,-9,2.5],
				"rot": [1,0,0,0]
			}
		},
		{
			"ATTOVERCOG": {
				"pos": [0,-0,30],
				"rot": [1,0,0,0]
			},
			"head": {
				"pos": [0,-0,6.775383],
				"rot": [0.974423,-0.019104,0.042809,-0.219778]
			},
			"leg1": {
				"pos": [-3,-9,2.5],
				"rot": [1,0,0,0]
			},
			"leg2": {
				"pos": [-9,-3.293288,3.549518],
				"rot": [0.994353,-0.023542,-0.023301,-0.100825]
			},
			"leg3": {
				"pos": [-9.159936,3.495370,3.370863],
				"rot": [0.974896,-0.022953,-0.062494,-0.212475]
			},
			"leg4": {
				"pos": [-3.156429,9,2.5],
				"rot": [0.999982,0,0,-0.006029]
			},
			"leg5": {
				"pos": [3,9,2.5],
				"rot": [1,0,0,0]
			},
			"leg6": {
				"pos": [9,3,2.5],
				"rot": [1,0,0,0]
			},
			"leg7": {
				"pos": [9,-3,2.5],
				"rot": [1,0,0,0]
			},
			"leg8": {
				"pos": [3,-9,2.5],
				"rot": [1,0,0,0]
			}
		},
		{
			"ATTOVERCOG": {
				"pos": [0,-0,30],
				"rot": [1,0,0,0]
			},
			"head": {
				"pos": [0,-0,6.752972],
				"rot": [0.975890,-0.018650,0.040827,-0.213600]
			},
			"leg1": {
				"pos": [-3,-9,2.5],
				"rot": [1,0,0,0]
			},
			"leg2": {
				"pos": [-9,-3.387573,3.886914],
				"rot": [0.990117,-0.032079,-0.029763,-0.133242]
			},
			"leg3": {
				"pos": [-9.008442,3.448583,3.090901],
				"rot": [0.985319,-0.003356,-0.051603,-0.162701]
			},
			"leg4": {
				"pos": [-3.102249,9,2.5],
				"rot": [0.999996,0,0,-0.002886]
			},
			"leg5": {
				"pos": [3,9,2.5],
				"rot": [1,0,0,0]
			},
			"leg6": {
				"pos": [9,3,2.5],
				"rot": [1,0,0,0]
			},
			"leg7": {
				"pos": [9,-3,2.5],
				"rot": [1,0,0,0]
			},
			"leg8": {
				"pos": [3,-9,2.5],
				"rot": [1,0,0,0]
			}
		},
		{
			"ATTOVERCOG": {
				"pos": [0,-0,30],
				"rot": [1,0,0,0]
			},
			"head": {
				"pos": [0,-0,6.726688],
				"rot": [0.977549,-0.018141,0.038707,-0.206327]
			},
			"leg1": {
				"pos": [-3,-9,2.5],
				"rot": [1,0,0,0]
			},
			"leg2": {
				"pos": [-9,-3.470802,4.184746],
				"rot": [0.985393,-0.039970,-0.035019,-0.161794]
			},
			"leg3": {
				"pos": [-8.874713,3.401142,2.843767],
				"rot": [0.992274,0.013135,-0.039799,-0.116771]
			},
			"leg4": {
				"pos": [-3.057669,9,2.5],
				"rot": [0.999999,0,0,-0.001116]
			},
			"leg5": {
				"pos": [3,9,2.5],
				"rot": [1,0,0,0]
			},
			"leg6": {
				"pos": [9,3,2.5],
				"rot": [1,0,0,0]
			},
			"leg7": {
				"pos": [9,-3,2.5],
				"rot": [1,0,0,0]
			},
			"leg8": {
				"pos": [3,-9,2.5],
				"rot": [1,0,0,0]
			}
		},
		{
			"ATTOVERCOG": {
				"pos": [0,-0,30],
				"rot": [1,0,0,0]
			},
			"head": {
				"pos": [0,-0,6.696720],
				"rot": [0.979365,-0.017569,0.036464,-0.198005]
			},
			"leg1": {
				"pos": [-3,-9,2.5],
				"rot": [1,0,0,0]
			},
			"leg2": {
				"pos": [-9,-3.534435,4.412456],
				"rot": [0.981156,-0.046216,-0.038744,-0.183562]
			},
			"leg3": {
				"pos": [-8.772470,3.356254,2.654820],
				"rot": [0.996138,0.025151,-0.028814,-0.079036]
			},
			"leg4": {
				"pos": [-3.025315,9,2.5],
				"rot": [1,0,0,-0.000299]
			},
			"leg5": {
				"pos": [3,9,2.5],
				"rot": [1,0,0,0]
			},
			"leg6": {
				"pos": [9,3,2.5],
				"rot": [1,0,0,0]
			},
			"leg7": {
				"pos": [9,-3,2.5],
				"rot": [1,0,0,0]
			},
			"leg8": {
				"pos": [3,-9,2.5],
				"rot": [1,0,0,0]
			}
		},
		{
			"ATTOVERCOG": {
				"pos": [0,-0,30],
				"rot": [1,0,0,0]
			},
			"head": {
				"pos": [0,-0,6.663319],
				"rot": [0.981296,-0.016928,0.034116,-0.188699]
			},
			"leg1": {
				"pos": [-3,-9,2.5],
				"rot": [1,0,0,0]
			},
			"leg2": {
				"pos": [-9,-3.573571,4.552503],
				"rot": [0.978282,-0.050143,-0.040906,-0.196917]
			},
			"leg3": {
				"pos": [-8.709587,3.316154,2.538613],
				"rot": [0.997919,0.032289,-0.020134,-0.052060]
			},
			"leg4": {
				"pos": [-3.006181,9,2.5],
				"rot": [1,0,0,-0.000034]
			},
			"leg5": {
				"pos": [3,9,2.5],
				"rot": [1,0,0,0]
			},
			"leg6": {
				"pos": [9,3,2.5],
				"rot": [1,0,0,0]
			},
			"leg7": {
				"pos": [9,-3,2.5],
				"rot": [1,0,0,0]
			},
			"leg8": {
				"pos": [3,-9,2.5],
				"rot": [1,0,0,0]
			}
		},
		{
			"ATTOVERCOG": {
				"pos": [0,-0,30],
				"rot": [1,0,0,0]
			},
			"head": {
				"pos": [0,-0,6.626806],
				"rot": [0.983297,-0.016215,0.031686,-0.178492]
			},
			"leg1": {
				"pos": [-3,-9,2.5],
				"rot": [1,0,0,0]
			},
			"leg2": {
				"pos": [-9,-3.586575,4.599037],
				"rot": [0.977282,-0.051463,-0.041602,-0.201349]
			},
			"leg3": {
				"pos": [-8.688693,3.282055,2.5],
				"rot": [0.998611,0.034756,-0.014652,-0.036781]
			},
			"leg4": {
				"pos": [-3,9,2.5],
				"rot": [1,0,0,0]
			},
			"leg5": {
				"pos": [3,9,2.5],
				"rot": [1,0,0,0]
			},
			"leg6": {
				"pos": [9,3,2.5],
				"rot": [1,0,0,0]
			},
			"leg7": {
				"pos": [9,-3,2.5],
				"rot": [1,0,0,0]
			},
			"leg8": {
				"pos": [3,-9,2.5],
				"rot": [1,0,0,0]
			}
		},
		{
			"ATTOVERCOG": {
				"pos": [0,-0,30],
				"rot": [1,0,0,0]
			},
			"head": {
				"pos": [0,-0,6.587567],
				"rot": [0.985321,-0.015427,0.029196,-0.167489]
			},
			"leg1": {
				"pos": [-3.030647,-9,2.564051],
				"rot": [0.999980,-0.000290,0.001731,-0.006081]
			},
			"leg2": {
				"pos": [-9,-3.585535,4.552503],
				"rot": [0.978336,-0.049076,-0.041121,-0.196873]
			},
			"leg3": {
				"pos": [-8.695595,3.249154,2.5],
				"rot": [0.998965,0.034199,-0.011073,-0.027856]
			},
			"leg4": {
				"pos": [-3,9,2.5],
				"rot": [1,0,0,0]
			},
			"leg5": {
				"pos": [3,9,2.5],
				"rot": [1,0,0,0]
			},
			"leg6": {
				"pos": [9,3,2.5],
				"rot": [1,0,0,0]
			},
			"leg7": {
				"pos": [9,-3,2.5],
				"rot": [1,0,0,0]
			},
			"leg8": {
				"pos": [3,-9,2.5],
				"rot": [1,0,0,0]
			}
		},
		{
			"ATTOVERCOG": {
				"pos": [0,-0,30],
				"rot": [1,0,0,0]
			},
			"head": {
				"pos": [0,-0,6.546056],
				"rot": [0.987319,-0.014563,0.026673,-0.155812]
			},
			"leg1": {
				"pos": [-3.122881,-9,2.756819],
				"rot": [0.999678,-0.001037,0.006962,-0.024374]
			},
			"leg2": {
				"pos": [-9,-3.582016,4.412456],
				"rot": [0.981349,-0.041925,-0.039547,-0.183391]
			},
			"leg3": {
				"pos": [-8.716365,3.212662,2.5],
				"rot": [0.999256,0.031992,-0.007909,-0.020032]
			},
			"leg4": {
				"pos": [-3,9,2.5],
				"rot": [1,0,0,0]
			},
			"leg5": {
				"pos": [3,9,2.5],
				"rot": [1,0,0,0]
			},
			"leg6": {
				"pos": [9,3,2.5],
				"rot": [1,0,0,0]
			},
			"leg7": {
				"pos": [9,-3,2.5],
				"rot": [1,0,0,0]
			},
			"leg8": {
				"pos": [3,-9,2.5],
				"rot": [1,0,0,0]
			}
		},
		{
			"ATTOVERCOG": {
				"pos": [0,-0,30],
				"rot": [1,0,0,0]
			},
			"head": {
				"pos": [0,-0,6.502783],
				"rot": [0.989247,-0.013628,0.024146,-0.143603]
			},
			"leg1": {
				"pos": [-3.272849,-9,3.070250],
				"rot": [0.998415,-0.001842,0.015519,-0.054072]
			},
			"leg2": {
				"pos": [-9,-3.575378,4.184747],
				"rot": [0.985734,-0.030402,-0.036588,-0.161446]
			},
			"leg3": {
				"pos": [-8.750136,3.173640,2.5],
				"rot": [0.999496,0.028251,-0.005265,-0.013485]
			},
			"leg4": {
				"pos": [-3,9,2.5],
				"rot": [1,0,0,0]
			},
			"leg5": {
				"pos": [3,9,2.5],
				"rot": [1,0,0,0]
			},
			"leg6": {
				"pos": [9,3,2.5],
				"rot": [1,0,0,0]
			},
			"leg7": {
				"pos": [9,-3,2.5],
				"rot": [1,0,0,0]
			},
			"leg8": {
				"pos": [3,-9,2.5],
				"rot": [1,0,0,0]
			}
		},
		{
			"ATTOVERCOG": {
				"pos": [0,-0,30],
				"rot": [1,0,0,0]
			},
			"head": {
				"pos": [0,-0,6.458305],
				"rot": [0.991063,-0.012628,0.021643,-0.131020]
			},
			"leg1": {
				"pos": [-3.468999,-9,3.480201],
				"rot": [0.995324,-0.002124,0.026776,-0.092784]
			},
			"leg2": {
				"pos": [-9,-3.565034,3.886914],
				"rot": [0.990515,-0.015552,-0.031983,-0.132726]
			},
			"leg3": {
				"pos": [-8.794307,3.133871,2.5],
				"rot": [0.999689,0.023288,-0.003210,-0.008344]
			},
			"leg4": {
				"pos": [-3,9,2.5],
				"rot": [1,0,0,0]
			},
			"leg5": {
				"pos": [3,9,2.5],
				"rot": [1,0,0,0]
			},
			"leg6": {
				"pos": [9,3,2.5],
				"rot": [1,0,0,0]
			},
			"leg7": {
				"pos": [9,-3,2.5],
				"rot": [1,0,0,0]
			},
			"leg8": {
				"pos": [3,-9,2.5],
				"rot": [1,0,0,0]
			}
		},
		{
			"ATTOVERCOG": {
				"pos": [0,-0,30],
				"rot": [1,0,0,0]
			},
			"head": {
				"pos": [0,-0,6.413217],
				"rot": [0.992733,-0.011572,0.019192,-0.118232]
			},
			"leg1": {
				"pos": [-3.691206,-9,3.944610],
				"rot": [0.989867,-0.001386,0.039556,-0.136371]
			},
			"leg2": {
				"pos": [-9,-3.550612,3.549519],
				"rot": [0.994631,0.000920,-0.025773,-0.100222]
			},
			"leg3": {
				"pos": [-8.844347,3.095775,2.5],
				"rot": [0.999832,0.017636,-0.001751,-0.004631]
			},
			"leg4": {
				"pos": [-3,9,2.5],
				"rot": [1,0,0,0]
			},
			"leg5": {
				"pos": [3,9,2.5],
				"rot": [1,0,0,0]
			},
			"leg6": {
				"pos": [9,3,2.5],
				"rot": [1,0,0,0]
			},
			"leg7": {
				"pos": [9,-3,2.5],
				"rot": [1,0,0,0]
			},
			"leg8": {
				"pos": [3,-9,2.5],
				"rot": [1,0,0,0]
			}
		},
		{
			"ATTOVERCOG": {
				"pos": [0,-0,30],
				"rot": [1,0,0,0]
			},
			"head": {
				"pos": [0,-0,6.368128],
				"rot": [0.994231,-0.010474,0.016821,-0.105414]
			},
			"leg1": {
				"pos": [-3.913413,-9,4.409018],
				"rot": [0.982354,0.000478,0.052290,-0.179574]
			},
			"leg2": {
				"pos": [-9,-3.532118,3.212123],
				"rot": [0.997382,0.016963,-0.018534,-0.067812]
			},
			"leg3": {
				"pos": [-8.894385,3.061971,2.5],
				"rot": [0.999926,0.011970,-0.000826,-0.002221]
			},
			"leg4": {
				"pos": [-3,9,2.5],
				"rot": [1,0,0,0]
			},
			"leg5": {
				"pos": [3,9,2.5],
				"rot": [1,0,0,0]
			},
			"leg6": {
				"pos": [9,3,2.5],
				"rot": [1,0,0,0]
			},
			"leg7": {
				"pos": [9,-3,2.5],
				"rot": [1,0,0,0]
			},
			"leg8": {
				"pos": [3,-9,2.5],
				"rot": [1,0,0,0]
			}
		},
		{
			"ATTOVERCOG": {
				"pos": [0,-0,30],
				"rot": [1,0,0,0]
			},
			"head": {
				"pos": [0,-0,6.323651],
				"rot": [0.995540,-0.009350,0.014554,-0.092744]
			},
			"leg1": {
				"pos": [-4.109564,-9,4.818970],
				"rot": [0.974034,0.003056,0.063433,-0.217311]
			},
			"leg2": {
				"pos": [-9,-3.509967,2.914290],
				"rot": [0.998690,0.030725,-0.011310,-0.039331]
			},
			"leg3": {
				"pos": [-8.938557,3.034646,2.5],
				"rot": [0.999975,0.006965,-0.000315,-0.000861]
			},
			"leg4": {
				"pos": [-3,9,2.5],
				"rot": [1,0,0,0]
			},
			"leg5": {
				"pos": [3,9,2.5],
				"rot": [1,0,0,0]
			},
			"leg6": {
				"pos": [9,3,2.5],
				"rot": [1,0,0,0]
			},
			"leg7": {
				"pos": [9,-3,2.5],
				"rot": [1,0,0,0]
			},
			"leg8": {
				"pos": [3,-9,2.5],
				"rot": [1,0,0,0]
			}
		},
		{
			"ATTOVERCOG": {
				"pos": [0,-0,30],
				"rot": [1,0,0,0]
			},
			"head": {
				"pos": [0,-0,6.280377],
				"rot": [0.996652,-0.008217,0.012414,-0.080394]
			},
			"leg1": {
				"pos": [-4.259531,-9,5.132400],
				"rot": [0.966621,0.005613,0.071856,-0.245864]
			},
			"leg2": {
				"pos": [-9,-3.484854,2.686581],
				"rot": [0.998990,0.040969,-0.005272,-0.017666]
			},
			"leg3": {
				"pos": [-8.972328,3.015094,2.5],
				"rot": [0.999995,0.003137,-0.000084,-0.000231]
			},
			"leg4": {
				"pos": [-3,9,2.5],
				"rot": [1,0,0,0]
			},
			"leg5": {
				"pos": [3,9,2.5],
				"rot": [1,0,0,0]
			},
			"leg6": {
				"pos": [9,3,2.5],
				"rot": [1,0,0,0]
			},
			"leg7": {
				"pos": [9,-3,2.5],
				"rot": [1,0,0,0]
			},
			"leg8": {
				"pos": [3,-9,2.5],
				"rot": [1,0,0,0]
			}
		},
		{
			"ATTOVERCOG": {
				"pos": [0,-0,30],
				"rot": [1,0,0,0]
			},
			"head": {
				"pos": [0,-0,6.238866],
				"rot": [0.997570,-0.007094,0.010419,-0.068528]
			},
			"leg1": {
				"pos": [-4.351766,-9,5.325168],
				"rot": [0.961614,0.007437,0.076983,-0.263282]
			},
			"leg2": {
				"pos": [-9,-3.457556,2.546534],
				"rot": [0.998878,0.047143,-0.001342,-0.004398]
			},
			"leg3": {
				"pos": [-8.993098,3.003662,2.5],
				"rot": [1,0.000782,-0.000009,-0.000026]
			},
			"leg4": {
				"pos": [-3,9,2.5],
				"rot": [1,0,0,0]
			},
			"leg5": {
				"pos": [3,9,2.5],
				"rot": [1,0,0,0]
			},
			"leg6": {
				"pos": [9,3,2.5],
				"rot": [1,0,0,0]
			},
			"leg7": {
				"pos": [9,-3,2.5],
				"rot": [1,0,0,0]
			},
			"leg8": {
				"pos": [3,-9,2.5],
				"rot": [1,0,0,0]
			}
		},
		{
			"ATTOVERCOG": {
				"pos": [0,-0,30],
				"rot": [1,0,0,0]
			},
			"head": {
				"pos": [0,-0,6.199628],
				"rot": [0.998302,-0.006001,0.008583,-0.057297]
			},
			"leg1": {
				"pos": [-4.382412,-9,5.389219],
				"rot": [0.959875,0.008085,0.078676,-0.269044]
			},
			"leg2": {
				"pos": [-9,-3.428772,2.5],
				"rot": [0.998790,0.049172,0,0]
			},
			"leg3": {
				"pos": [-9,3,2.5],
				"rot": [1,0,0,0]
			},
			"leg4": {
				"pos": [-3,9,2.5],
				"rot": [1,0,0,0]
			},
			"leg5": {
				"pos": [3,9,2.5],
				"rot": [1,0,0,0]
			},
			"leg6": {
				"pos": [9,3,2.5],
				"rot": [1,0,0,0]
			},
			"leg7": {
				"pos": [9,-3,2.5],
				"rot": [1,0,0,0]
			},
			"leg8": {
				"pos": [3,-9,2.5],
				"rot": [1,0,0,0]
			}
		},
		{
			"ATTOVERCOG": {
				"pos": [0,-0,30],
				"rot": [1,0,0,0]
			},
			"head": {
				"pos": [0,-0,6.163115],
				"rot": [0.998866,-0.004957,0.006919,-0.046835]
			},
			"leg1": {
				"pos": [-4.351766,-9,5.325168],
				"rot": [0.961614,0.007437,0.076983,-0.263282]
			},
			"leg2": {
				"pos": [-9,-3.393981,2.5],
				"rot": [0.998843,0.048082,0,0]
			},
			"leg3": {
				"pos": [-9,3,2.5],
				"rot": [1,0,0,0]
			},
			"leg4": {
				"pos": [-3,9,2.5],
				"rot": [1,0,0,0]
			},
			"leg5": {
				"pos": [3,9,2.5],
				"rot": [1,0,0,0]
			},
			"leg6": {
				"pos": [9,3,2.5],
				"rot": [1,0,0,0]
			},
			"leg7": {
				"pos": [9,-3,2.5],
				"rot": [1,0,0,0]
			},
			"leg8": {
				"pos": [3,-9,2.5],
				"rot": [1,0,0,0]
			}
		},
		{
			"ATTOVERCOG": {
				"pos": [0,-0,30],
				"rot": [1,0,0,0]
			},
			"head": {
				"pos": [0,-0,6.129714],
				"rot": [0.999283,-0.003979,0.005433,-0.037256]
			},
			"leg1": {
				"pos": [-4.259531,-9,5.132400],
				"rot": [0.966621,0.005613,0.071856,-0.245864]
			},
			"leg2": {
				"pos": [-9,-3.348604,2.5],
				"rot": [0.998996,0.044804,0,0]
			},
			"leg3": {
				"pos": [-9,3,2.5],
				"rot": [1,0,0,0]
			},
			"leg4": {
				"pos": [-3,9,2.5],
				"rot": [1,0,0,0]
			},
			"leg5": {
				"pos": [3,9,2.5],
				"rot": [1,0,0,0]
			},
			"leg6": {
				"pos": [9,3,2.5],
				"rot": [1,0,0,0]
			},
			"leg7": {
				"pos": [9,-3,2.5],
				"rot": [1,0,0,0]
			},
			"leg8": {
				"pos": [3,-9,2.5],
				"rot": [1,0,0,0]
			}
		},
		{
			"ATTOVERCOG": {
				"pos": [0,-0,30],
				"rot": [1,0,0,0]
			},
			"head": {
				"pos": [0,-0,6.099745],
				"rot": [0.999576,-0.003085,0.004129,-0.028655]
			},
			"leg1": {
				"pos": [-4.109564,-9,4.818970],
				"rot": [0.974034,0.003056,0.063433,-0.217311]
			},
			"leg2": {
				"pos": [-9,-3.294096,2.5],
				"rot": [0.999221,0.039472,0,0]
			},
			"leg3": {
				"pos": [-9,3,2.5],
				"rot": [1,0,0,0]
			},
			"leg4": {
				"pos": [-3,9,2.5],
				"rot": [1,0,0,0]
			},
			"leg5": {
				"pos": [3,9,2.5],
				"rot": [1,0,0,0]
			},
			"leg6": {
				"pos": [9,3,2.5],
				"rot": [1,0,0,0]
			},
			"leg7": {
				"pos": [9,-3,2.5],
				"rot": [1,0,0,0]
			},
			"leg8": {
				"pos": [3,-9,2.5],
				"rot": [1,0,0,0]
			}
		},
		{
			"ATTOVERCOG": {
				"pos": [0,-0,30],
				"rot": [1,0,0,0]
			},
			"head": {
				"pos": [0,-0,6.073461],
				"rot": [0.999770,-0.002287,0.003008,-0.021108]
			},
			"leg1": {
				"pos": [-3.913413,-9,4.409018],
				"rot": [0.982354,0.000478,0.052290,-0.179574]
			},
			"leg2": {
				"pos": [-9,-3.233497,2.5],
				"rot": [0.999472,0.032497,0,0]
			},
			"leg3": {
				"pos": [-9,3,2.5],
				"rot": [1,0,0,0]
			},
			"leg4": {
				"pos": [-3,9,2.5],
				"rot": [1,0,0,0]
			},
			"leg5": {
				"pos": [3,9,2.5],
				"rot": [1,0,0,0]
			},
			"leg6": {
				"pos": [9,3,2.5],
				"rot": [1,0,0,0]
			},
			"leg7": {
				"pos": [9,-3,2.5],
				"rot": [1,0,0,0]
			},
			"leg8": {
				"pos": [3,-9,2.5],
				"rot": [1,0,0,0]
			}
		},
		{
			"ATTOVERCOG": {
				"pos": [0,-0,30],
				"rot": [1,0,0,0]
			},
			"head": {
				"pos": [0,-0,6.051050],
				"rot": [0.999889,-0.001598,0.002070,-0.014671]
			},
			"leg1": {
				"pos": [-3.691206,-9,3.944610],
				"rot": [0.989867,-0.001386,0.039556,-0.136371]
			},
			"leg2": {
				"pos": [-9,-3.171448,2.5],
				"rot": [0.999698,0.024593,0,0]
			},
			"leg3": {
				"pos": [-9,3,2.5],
				"rot": [1,0,0,0]
			},
			"leg4": {
				"pos": [-3,9,2.5],
				"rot": [1,0,0,0]
			},
			"leg5": {
				"pos": [3,9,2.5],
				"rot": [1,0,0,0]
			},
			"leg6": {
				"pos": [9,3,2.5],
				"rot": [1,0,0,0]
			},
			"leg7": {
				"pos": [9,-3,2.5],
				"rot": [1,0,0,0]
			},
			"leg8": {
				"pos": [3,-9,2.5],
				"rot": [1,0,0,0]
			}
		},
		{
			"ATTOVERCOG": {
				"pos": [0,-0,30],
				"rot": [1,0,0,0]
			},
			"head": {
				"pos": [0,-0,6.032644],
				"rot": [0.999955,-0.001026,0.001313,-0.009382]
			},
			"leg1": {
				"pos": [-3.469000,-9,3.480201],
				"rot": [0.995324,-0.002124,0.026776,-0.092784]
			},
			"leg2": {
				"pos": [-9,-3.113471,2.5],
				"rot": [0.999861,0.016688,0,0]
			},
			"leg3": {
				"pos": [-9,3,2.5],
				"rot": [1,0,0,0]
			},
			"leg4": {
				"pos": [-3,9,2.5],
				"rot": [1,0,0,0]
			},
			"leg5": {
				"pos": [3,9,2.5],
				"rot": [1,0,0,0]
			},
			"leg6": {
				"pos": [9,3,2.5],
				"rot": [1,0,0,0]
			},
			"leg7": {
				"pos": [9,-3,2.5],
				"rot": [1,0,0,0]
			},
			"leg8": {
				"pos": [3,-9,2.5],
				"rot": [1,0,0,0]
			}
		},
		{
			"ATTOVERCOG": {
				"pos": [0,-0,30],
				"rot": [1,0,0,0]
			},
			"head": {
				"pos": [0,-0,6.018321],
				"rot": [0.999986,-0.000577,0.000731,-0.005266]
			},
			"leg1": {
				"pos": [-3.272849,-9,3.070249],
				"rot": [0.998415,-0.001842,0.015519,-0.054072]
			},
			"leg2": {
				"pos": [-9,-3.064678,2.5],
				"rot": [0.999953,0.009709,0,0]
			},
			"leg3": {
				"pos": [-9,3,2.5],
				"rot": [1,0,0,0]
			},
			"leg4": {
				"pos": [-3,9,2.5],
				"rot": [1,0,0,0]
			},
			"leg5": {
				"pos": [3,9,2.5],
				"rot": [1,0,0,0]
			},
			"leg6": {
				"pos": [9,3,2.5],
				"rot": [1,0,0,0]
			},
			"leg7": {
				"pos": [9,-3,2.5],
				"rot": [1,0,0,0]
			},
			"leg8": {
				"pos": [3,-9,2.5],
				"rot": [1,0,0,0]
			}
		},
		{
			"ATTOVERCOG": {
				"pos": [0,-0,30],
				"rot": [1,0,0,0]
			},
			"head": {
				"pos": [0,-0,6.008114],
				"rot": [0.999997,-0.000256,0.000322,-0.002332]
			},
			"leg1": {
				"pos": [-3.122881,-9,2.756819],
				"rot": [0.999678,-0.001037,0.006962,-0.024374]
			},
			"leg2": {
				"pos": [-9,-3.028646,2.5],
				"rot": [0.999990,0.004373,0,0]
			},
			"leg3": {
				"pos": [-9,3,2.5],
				"rot": [1,0,0,0]
			},
			"leg4": {
				"pos": [-3,9,2.5],
				"rot": [1,0,0,0]
			},
			"leg5": {
				"pos": [3,9,2.5],
				"rot": [1,0,0,0]
			},
			"leg6": {
				"pos": [9,3,2.5],
				"rot": [1,0,0,0]
			},
			"leg7": {
				"pos": [9,-3,2.5],
				"rot": [1,0,0,0]
			},
			"leg8": {
				"pos": [3,-9,2.5],
				"rot": [1,0,0,0]
			}
		},
		{
			"ATTOVERCOG": {
				"pos": [0,-0,30],
				"rot": [1,0,0,0]
			},
			"head": {
				"pos": [0,-0,6.002019],
				"rot": [1,-0.000064,0.000080,-0.000580]
			},
			"leg1": {
				"pos": [-3.030647,-9,2.564052],
				"rot": [0.999980,-0.000290,0.001731,-0.006081]
			},
			"leg2": {
				"pos": [-9,-3.007047,2.5],
				"rot": [0.999999,0.001091,0,0]
			},
			"leg3": {
				"pos": [-9,3,2.5],
				"rot": [1,0,0,0]
			},
			"leg4": {
				"pos": [-3,9,2.5],
				"rot": [1,0,0,0]
			},
			"leg5": {
				"pos": [3,9,2.5],
				"rot": [1,0,0,0]
			},
			"leg6": {
				"pos": [9,3,2.5],
				"rot": [1,0,0,0]
			},
			"leg7": {
				"pos": [9,-3,2.5],
				"rot": [1,0,0,0]
			},
			"leg8": {
				"pos": [3,-9,2.5],
				"rot": [1,0,0,0]
			}
		},
		{
			"ATTOVERCOG": {
				"pos": [0,-0,30],
				"rot": [1,0,0,0]
			},
			"head": {
				"pos": [0,-0,6],
				"rot": [1,0,0,0]
			},
			"leg1": {
				"pos": [-3,-9,2.5],
				"rot": [1,0,0,0]
			},
			"leg2": {
				"pos": [-9,-3,2.5],
				"rot": [1,0,0,0]
			},
			"leg3": {
				"pos": [-9,3,2.5],
				"rot": [1,0,0,0]
			},
			"leg4": {
				"pos": [-3,9,2.5],
				"rot": [1,0,0,0]
			},
			"leg5": {
				"pos": [3,9,2.5],
				"rot": [1,0,0,0]
			},
			"leg6": {
				"pos": [9,3,2.5],
				"rot": [1,0,0,0]
			},
			"leg7": {
				"pos": [9,-3,2.5],
				"rot": [1,0,0,0]
			},
			"leg8": {
				"pos": [3,-9,2.5],
				"rot": [1,0,0,0]
			}
		}
	]
}