{
	"type": "arc",
	"rarity": "common",
	"encounters": {
		"start": "file(encounters/start.json)",
		"introduction_dialogue": "file(encounters/introduction_dialogue.json)",

		"add_archipelago_crops":"file(encounters/add_archipelago_crops.json)",

		"wait_first_soldier":"file(encounters/wait_first_soldier.json)",
		"miranda_before_selling_clay":"file(encounters/miranda_before_selling_clay.json)",
		"miranda_clay_shop":"file(encounters/miranda_clay_shop.json)",
		"miranda_notice_a_lost_crate":"file(encounters/miranda_notice_a_lost_crate.json)",
		"spawn_crate":"file(encounters/spawn_crate.json)",
		"wait_after_spawn_crate":"file(encounters/wait_after_spawn_crate.json)",
		"is_crate_destroyed":"file(encounters/is_crate_destroyed.json)",
		"crate_destroyed":"file(encounters/crate_destroyed.json)",
		"teaches_how_to_break_crate":"file(encounters/teaches_how_to_break_crate.json)",
		"miranda_talks_about_cocolings":"file(encounters/miranda_talks_about_cocolings.json)",
		"wait_to_spawn_crate_again":"file(encounters/wait_to_spawn_crate_again.json)",
		"miranda_notice_another_crate":"file(encounters/miranda_notice_another_crate.json)",
		"spawn_crate_again":"file(encounters/spawn_crate_again.json)"
	}
}