{
	"ai": {
		"stonehearth:top": {
			"children": {
				"stonehearth:work": {
					"children": {
						"archipelago_biome:task_group:fisher": {
							"type": "task_group",
							"work_order": "job",
							"children": {
								"stonehearth:harvest_resource": {
									"type": "task",
									"args": {
										"category": "fisher"
									},
									"priority": 10
								},
								"stonehearth:harvest_renewable_resource": {
									"type": "task",
									"args": {
										"category": "fisher"
									},
									"priority": 10
								}
							}
						}
					}
				}
			}
		}
	}
}